Workbook

Sheet Summary
A1: AgentGuard Risk & Vulnerability Catalog | B1: AgentGuard Risk & Vulnerability Catalog | C1: AgentGuard Risk & Vulnerability Catalog | D1: AgentGuard Risk & Vulnerability Catalog | E1: AgentGuard Risk & Vulnerability Catalog | F1: AgentGuard Risk & Vulnerability Catalog | G1: AgentGuard Risk & Vulnerability Catalog | H1: AgentGuard Risk & Vulnerability Catalog | I1: AgentGuard Risk & Vulnerability Catalog | J1: AgentGuard Risk & Vulnerability Catalog | K1: AgentGuard Risk & Vulnerability Catalog | L1: AgentGuard Risk & Vulnerability Catalog | M1: AgentGuard Risk & Vulnerability Catalog | N1: AgentGuard Risk & Vulnerability Catalog | O1: AgentGuard Risk & Vulnerability Catalog | P1: AgentGuard Risk & Vulnerability Catalog | Q1: AgentGuard Risk & Vulnerability Catalog
A2: AgentGuard Risk & Vulnerability Catalog | B2: AgentGuard Risk & Vulnerability Catalog | C2: AgentGuard Risk & Vulnerability Catalog | D2: AgentGuard Risk & Vulnerability Catalog | E2: AgentGuard Risk & Vulnerability Catalog | F2: AgentGuard Risk & Vulnerability Catalog | G2: AgentGuard Risk & Vulnerability Catalog | H2: AgentGuard Risk & Vulnerability Catalog | I2: AgentGuard Risk & Vulnerability Catalog | J2: AgentGuard Risk & Vulnerability Catalog | K2: AgentGuard Risk & Vulnerability Catalog | L2: AgentGuard Risk & Vulnerability Catalog | M2: AgentGuard Risk & Vulnerability Catalog | N2: AgentGuard Risk & Vulnerability Catalog | O2: AgentGuard Risk & Vulnerability Catalog | P2: AgentGuard Risk & Vulnerability Catalog | Q2: AgentGuard Risk & Vulnerability Catalog
A3: Formula-driven overview of native AgentGuard, custom, and NVIDIA SkillSpector rules
A5: Total Rules | B5: AgentGuard Engine | C5: SkillSpector Engine | D5: Critical | E5: High | F5: Native Rules
A6: =COUNTA('Risk_rule Catalog'!$A$2:$A$182) -> 181 | B6: =COUNTIF('Risk_rule Catalog'!$C$2:$C$182,"agentguard") -> 113 | C6: =COUNTIF('Risk_rule Catalog'!$C$2:$C$182,"skillspector") -> 68 | D6: =COUNTIF('Risk_rule Catalog'!$F$2:$F$182,"Critical") -> 73 | E6: =COUNTIF('Risk_rule Catalog'!$F$2:$F$182,"High") -> 83 | F6: =COUNTIF('Risk_rule Catalog'!$D$2:$D$182,"Native") -> 112
A8: Severity | B8: Rule Count | D8: Analysis Type | E8: Rule Count | G8: Rule Set | H8: Rule Count
A9: Critical | B9: =COUNTIF('Risk_rule Catalog'!$F$2:$F$182,A9) -> 73 | D9: taint | E9: =COUNTIF('Risk_rule Catalog'!$G$2:$G$182,D9) -> 75 | G9: Native | H9: =COUNTIF('Risk_rule Catalog'!$D$2:$D$182,G9) -> 112
A10: High | B10: =COUNTIF('Risk_rule Catalog'!$F$2:$F$182,A10) -> 83 | D10: config | E10: =COUNTIF('Risk_rule Catalog'!$G$2:$G$182,D10) -> 22 | G10: Custom | H10: =COUNTIF('Risk_rule Catalog'!$D$2:$D$182,G10) -> 1
A11: Medium | B11: =COUNTIF('Risk_rule Catalog'!$F$2:$F$182,A11) -> 22 | D11: external | E11: =COUNTIF('Risk_rule Catalog'!$G$2:$G$182,D11) -> 68 | G11: Integration | H11: =COUNTIF('Risk_rule Catalog'!$D$2:$D$182,G11) -> 68
A12: Low | B12: =COUNTIF('Risk_rule Catalog'!$F$2:$F$182,A12) -> 3 | D12: secret | E12: =COUNTIF('Risk_rule Catalog'!$G$2:$G$182,D12) -> 5
D13: structural | E13: =COUNTIF('Risk_rule Catalog'!$G$2:$G$182,D13) -> 4
D14: control_flow | E14: =COUNTIF('Risk_rule Catalog'!$G$2:$G$182,D14) -> 4
D15: dependency | E15: =COUNTIF('Risk_rule Catalog'!$G$2:$G$182,D15) -> 3
A18: Catalog Scope | B18: Catalog Scope | C18: Catalog Scope | D18: Catalog Scope | E18: Catalog Scope | F18: Catalog Scope | G18: Catalog Scope | H18: Catalog Scope
A19: Includes all YAML rule definitions currently loaded from rules/builtin, rules/custom, and rules/integrations. SkillSpector entries are external-engine metadata and require the separately installed NVIDIA CLI. | B19: Includes all YAML rule definitions currently loaded from rules/builtin, rules/custom, and rules/integrations. SkillSpector entries are external-engine metadata and require the separately installed NVIDIA CLI. | C19: Includes all YAML rule definitions currently loaded from rules/builtin, rules/custom, and rules/integrations. SkillSpector entries are external-engine metadata and require the separately installed NVIDIA CLI. | D19: Includes all YAML rule definitions currently loaded from rules/builtin, rules/custom, and rules/integrations. SkillSpector entries are external-engine metadata and require the separately installed NVIDIA CLI. | E19: Includes all YAML rule definitions currently loaded from rules/builtin, rules/custom, and rules/integrations. SkillSpector entries are external-engine metadata and require the separately installed NVIDIA CLI. | F19: Includes all YAML rule definitions currently loaded from rules/builtin, rules/custom, and rules/integrations. SkillSpector entries are external-engine metadata and require the separately installed NVIDIA CLI. | G19: Includes all YAML rule definitions currently loaded from rules/builtin, rules/custom, and rules/integrations. SkillSpector entries are external-engine metadata and require the separately installed NVIDIA CLI. | H19: Includes all YAML rule definitions currently loaded from rules/builtin, rules/custom, and rules/integrations. SkillSpector entries are external-engine metadata and require the separately installed NVIDIA CLI.
A20: Includes all YAML rule definitions currently loaded from rules/builtin, rules/custom, and rules/integrations. SkillSpector entries are external-engine metadata and require the separately installed NVIDIA CLI. | B20: Includes all YAML rule definitions currently loaded from rules/builtin, rules/custom, and rules/integrations. SkillSpector entries are external-engine metadata and require the separately installed NVIDIA CLI. | C20: Includes all YAML rule definitions currently loaded from rules/builtin, rules/custom, and rules/integrations. SkillSpector entries are external-engine metadata and require the separately installed NVIDIA CLI. | D20: Includes all YAML rule definitions currently loaded from rules/builtin, rules/custom, and rules/integrations. SkillSpector entries are external-engine metadata and require the separately installed NVIDIA CLI. | E20: Includes all YAML rule definitions currently loaded from rules/builtin, rules/custom, and rules/integrations. SkillSpector entries are external-engine metadata and require the separately installed NVIDIA CLI. | F20: Includes all YAML rule definitions currently loaded from rules/builtin, rules/custom, and rules/integrations. SkillSpector entries are external-engine metadata and require the separately installed NVIDIA CLI. | G20: Includes all YAML rule definitions currently loaded from rules/builtin, rules/custom, and rules/integrations. SkillSpector entries are external-engine metadata and require the separately installed NVIDIA CLI. | H20: Includes all YAML rule definitions currently loaded from rules/builtin, rules/custom, and rules/integrations. SkillSpector entries are external-engine metadata and require the separately installed NVIDIA CLI.
A21: https://github.com/akarshkn17/AgentGuard | B21: https://github.com/akarshkn17/AgentGuard | C21: https://github.com/akarshkn17/AgentGuard | D21: https://github.com/akarshkn17/AgentGuard | E21: https://github.com/akarshkn17/AgentGuard | F21: https://github.com/akarshkn17/AgentGuard | G21: https://github.com/akarshkn17/AgentGuard | H21: https://github.com/akarshkn17/AgentGuard

Sheet Risk_rule Catalog
A1: Rule ID | B1: Name | C1: Engine | D1: Rule Set | E1: Category | F1: Severity | G1: Analysis Type | H1: Targets | I1: Sources | J1: Sinks | K1: Barriers | L1: Message | M1: Detection Logic | N1: Remediation | O1: Source Description | P1: Sink Description | Q1: Source File | R1: Source URL | S1: Mapped Security Controls
A2: CUSTOM-AI-001 | B2: Example organization admin command rule | C2: agentguard | D2: Custom | E2: custom | F2: Critical | G2: taint | H2: agent, tool | I2: llm_output | J2: shell_execution | K2: command_allowlist, authorization_check | L2: LLM output reaches a custom privileged command API. | N2: Use a fixed operation enum and deterministic authorization before execution. | Q2: rules/custom/example.yaml | R2: https://github.com/akarshkn17/AgentGuard/blob/main/rules/custom/example.yaml | S2: SEC_06 (Structured Output Schema + Tool Name Auth); IAM_04 (User Identity Propagation - AgentAuthContext); SEC_18 (Human-in-the-Loop for High-Risk Actions); MON_04 (Tool Invocation Monitoring + Auto-Response); IR_01 (Multi-Level Kill-Switch Model)
A3: AIR-AGENT-001 | B3: Unbounded recursion or iteration in agent loop | C3: agentguard | D3: Native | E3: Agent Orchestration | F3: High | G3: config | H3: agent | L3: Unbounded recursion or iteration in agent loop | M3: Flag agent loops lacking max iterations/recursion limit or set to extremely high/unlimited. | N3: Hard step/recursion limit | O3: N/A | P3: while agent continues, recursion_limit absent/excessive | Q3: rules/builtin/agent_orchestration.yaml | R3: https://github.com/akarshkn17/AgentGuard/blob/main/rules/builtin/agent_orchestration.yaml | S3: SEC_16 (Recursive Loop & Runaway Prevention); BIZ_06 (Cost and Abuse Budgeting); MON_08 (Behavioral Analytics & Anomaly Detection); IR_01 (Multi-Level Kill-Switch Model)
A4: AIR-AGENT-002 | B4: Unbounded retry of LLM/tool calls | C4: agentguard | D4: Native | E4: Agent Orchestration | F4: High | G4: config | H4: agent | L4: Unbounded retry of LLM/tool calls | M4: Flag retry decorators/loops with no max attempts around model/tool/network calls. | N4: Max retry count + timeout + budget | O4: N/A | P4: retry loops/backoff handlers | Q4: rules/builtin/agent_orchestration.yaml | R4: https://github.com/akarshkn17/AgentGuard/blob/main/rules/builtin/agent_orchestration.yaml | S4: SEC_16 (Recursive Loop & Runaway Prevention); BIZ_06 (Cost and Abuse Budgeting); MON_08 (Behavioral Analytics & Anomaly Detection); IR_01 (Multi-Level Kill-Switch Model)
A5: AIR-AGENT-003 | B5: No timeout on external tool or model call | C5: agentguard | D5: Native | E5: Agent Orchestration | F5: Medium | G5: config | H5: agent | J5: shell_execution | L5: No timeout on external tool or model call | M5: Flag external calls in agent/tool code with absent timeout where API supports one; confidence-based. | N5: Finite timeout | O5: N/A | P5: HTTP/model/subprocess/tool call | Q5: rules/builtin/agent_orchestration.yaml | R5: https://github.com/akarshkn17/AgentGuard/blob/main/rules/builtin/agent_orchestration.yaml | S5: SEC_16 (Recursive Loop & Runaway Prevention); BIZ_06 (Cost and Abuse Budgeting); MON_08 (Behavioral Analytics & Anomaly Detection); IR_01 (Multi-Level Kill-Switch Model)
A6: AIR-AGENT-004 | B6: No token/context budget before model invocation | C6: agentguard | D6: Native | E6: Agent Orchestration | F6: High | G6: config | H6: agent | L6: No token/context budget before model invocation | M6: Flag unbounded collection/history/document concatenation into prompts with no length/token cap. | N6: Maximum input size/token budget/truncation | O6: Documents/history/retrieval context | P6: LLM invocation | Q6: rules/builtin/agent_orchestration.yaml | R6: https://github.com/akarshkn17/AgentGuard/blob/main/rules/builtin/agent_orchestration.yaml | S6: SEC_07 (Token Budget Monitoring - Prompt Stuffing Defense); BIZ_06 (Cost and Abuse Budgeting); MON_08 (Behavioral Analytics & Anomaly Detection)
A7: AIR-AGENT-005 | B7: Parallel agents share mutable global state | C7: agentguard | D7: Native | E7: Agent Orchestration | F7: High | G7: structural | H7: agent | L7: Parallel agents share mutable global state | M7: Flag global mutable conversation/memory/tool state accessed by concurrent agent handlers. | N7: Per-session isolated state store | O7: Multiple sessions/agents | P7: module/global mutable dict/list/state object | Q7: rules/builtin/agent_orchestration.yaml | R7: https://github.com/akarshkn17/AgentGuard/blob/main/rules/builtin/agent_orchestration.yaml | S7: REG_02 (Agent Manifest Schema Validation); MEM_01 (Memory Store Classification and Ownership); MEM_02 (Memory Read Authorization and ACL Filtering); MON_08 (Behavioral Analytics & Anomaly Detection)
A8: AIR-AGENT-006 | B8: Model output selects arbitrary callable/function by name | C8: agentguard | D8: Native | E8: Agent Orchestration | F8: Critical | G8: taint | H8: agent | I8: llm_output | K8: allowlist | L8: Model output selects arbitrary callable/function by name | M8: Flag model-controlled name used in dynamic callable lookup/invocation without allowlist. | N8: Allowlisted registry with fixed capability set | O8: LLM output function/tool name | P8: globals(), getattr(), registry lookup followed by call | Q8: rules/builtin/agent_orchestration.yaml | R8: https://github.com/akarshkn17/AgentGuard/blob/main/rules/builtin/agent_orchestration.yaml | S8: SEC_06 (Structured Output Schema + Tool Name Auth); REG_02 (Agent Manifest Schema Validation); SEC_21 (Policy-as-Code for AI Controls); MON_04 (Tool Invocation Monitoring + Auto-Response); IR_01 (Multi-Level Kill-Switch Model)
A9: AIR-AGENT-007 | B9: Agent can dynamically install/load new tools during execution | C9: agentguard | D9: Native | E9: Agent Orchestration | F9: Critical | G9: taint | H9: agent | I9: llm_output, user_input | L9: Agent can dynamically install/load new tools during execution | M9: Flag model/user-controlled dynamic tool registration, package install, plugin load, or MCP server connection. | N9: Admin-approved signed registry only | O9: Model/user tool/package/server identifier | P9: tool installer/registry/import/MCP connect | Q9: rules/builtin/agent_orchestration.yaml | R9: https://github.com/akarshkn17/AgentGuard/blob/main/rules/builtin/agent_orchestration.yaml | S9: REG_01 (Authoritative Agent Registry); REG_03 (AIBOM Required for Every Agent); SEC_15 (Agent Registry Compliance Gate); REG_07 (Runtime Drift Detection Against Registry); SEC_20 (AIBOM - AI Bill of Materials); IR_01 (Multi-Level Kill-Switch Model)
A10: AIR-AGENT-008 | B10: Planner-generated arguments bypass typed tool interface | C10: agentguard | D10: Native | E10: Agent Orchestration | F10: High | G10: taint | H10: agent | I10: llm_output | K10: schema_validation | L10: Planner-generated arguments bypass typed tool interface | M10: Flag generic dispatcher that forwards model-produced dicts to callables without per-tool validation. | N10: Per-tool typed schema and validation | O10: Planner raw text/JSON | P10: generic dispatch **kwargs/dict to arbitrary tool | Q10: rules/builtin/agent_orchestration.yaml | R10: https://github.com/akarshkn17/AgentGuard/blob/main/rules/builtin/agent_orchestration.yaml | S10: SEC_06 (Structured Output Schema + Tool Name Auth); REG_02 (Agent Manifest Schema Validation); SEC_21 (Policy-as-Code for AI Controls); MON_04 (Tool Invocation Monitoring + Auto-Response)
A11: AIR-AGENT-009 | B11: Sub-agent can call parent-only privileged tools | C11: agentguard | D11: Native | E11: Agent Orchestration | F11: Critical | G11: config | H11: multi-agent | L11: Sub-agent can call parent-only privileged tools | M11: Build agent-to-tool graph; flag privileged tool bound to or reachable by unauthorized sub-agents. | N11: Per-agent capability set | O11: Sub-agent execution context | P11: privileged parent tool | Q11: rules/builtin/agent_orchestration.yaml | R11: https://github.com/akarshkn17/AgentGuard/blob/main/rules/builtin/agent_orchestration.yaml | S11: IAM_03 (Least-Privilege Resource-Scoped IAM); IAM_14 (Agent-to-Agent Trust Scoping); REG_02 (Agent Manifest Schema Validation); SEC_15 (Agent Registry Compliance Gate); MON_04 (Tool Invocation Monitoring + Auto-Response); IR_01 (Multi-Level Kill-Switch Model)
A12: AIR-AGENT-010 | B12: Agent-to-agent messages can spoof system/internal role | C12: agentguard | D12: Native | E12: Agent Orchestration | F12: Critical | G12: taint | H12: multi-agent | L12: Agent-to-agent messages can spoof system/internal role | M12: Flag remote agent content accepted with caller-supplied privileged role/type. | N12: Authenticated channel + fixed role assignment | O12: Remote/sub-agent message | P12: system/internal message channel | Q12: rules/builtin/agent_orchestration.yaml | R12: https://github.com/akarshkn17/AgentGuard/blob/main/rules/builtin/agent_orchestration.yaml | S12: IAM_05 (A2A Delegation Bundle Validation); IAM_14 (Agent-to-Agent Trust Scoping); SEC_04 (A2A Inbound Content Filtering); MON_03 (Decision Trace Logging - Tool, Policy and Evidence Trace); IR_01 (Multi-Level Kill-Switch Model)
A13: AIR-AUTH-001 | B13: Tool authorization does not bind to initiating user identity | C13: agentguard | D13: Native | E13: Authorization | F13: Critical | G13: control_flow | H13: agent, tool | K13: rbac_check | L13: Tool authorization does not bind to initiating user identity | M13: Flag sensitive tool functions lacking user/principal parameter or authorization call before side effect. | N13: Propagate identity and enforce RBAC/ABAC at tool boundary | O13: Authenticated user identity | P13: sensitive tool handler | Q13: rules/builtin/authorization.yaml | R13: https://github.com/akarshkn17/AgentGuard/blob/main/rules/builtin/authorization.yaml | S13: IAM_04 (User Identity Propagation - AgentAuthContext); IAM_03 (Least-Privilege Resource-Scoped IAM); MON_03 (Decision Trace Logging - Tool, Policy and Evidence Trace); SEC_18 (Human-in-the-Loop for High-Risk Actions)
A14: AIR-AUTH-002 | B14: Cross-agent delegation drops authorization context | C14: agentguard | D14: Native | E14: Authorization | F14: Critical | G14: taint | H14: multi-agent | L14: Cross-agent delegation drops authorization context | M14: Track identity object across agent call graph; flag delegation where identity is absent/replaced with service identity only. | N14: Propagate signed identity/claims and reduce privileges | O14: User principal/claims/tenant | P14: sub-agent invocation / remote agent call | Q14: rules/builtin/authorization.yaml | R14: https://github.com/akarshkn17/AgentGuard/blob/main/rules/builtin/authorization.yaml | S14: IAM_05 (A2A Delegation Bundle Validation); IAM_04 (User Identity Propagation - AgentAuthContext); IAM_14 (Agent-to-Agent Trust Scoping); IAM_13 (Federated Identity Subject Consistency Verification); MON_03 (Decision Trace Logging - Tool, Policy and Evidence Trace); IR_01 (Multi-Level Kill-Switch Model)
A15: AIR-AUTH-003 | B15: Agent identity trusted from spoofable header/string | C15: agentguard | D15: Native | E15: Identity | F15: Critical | G15: taint | H15: agent, tool, mcp | I15: user_input | J15: authorization_decision | L15: Agent identity trusted from spoofable header/string | M15: Flag request/model-controlled identity strings used in allow/deny checks. | N15: Verified signed token/workload identity | O15: X-Agent-Name, agent_id, role, caller name from request/model | P15: authorization decision | Q15: rules/builtin/identity.yaml | R15: https://github.com/akarshkn17/AgentGuard/blob/main/rules/builtin/identity.yaml | S15: IAM_13 (Federated Identity Subject Consistency Verification); IAM_05 (A2A Delegation Bundle Validation); IAM_04 (User Identity Propagation - AgentAuthContext); MON_03 (Decision Trace Logging - Tool, Policy and Evidence Trace); IR_01 (Multi-Level Kill-Switch Model)
A16: AIR-AUTH-004 | B16: Runtime service account uses wildcard/broad cloud permissions | C16: agentguard | D16: Native | E16: Authorization | F16: Critical | G16: config | H16: agent_runtime | L16: Runtime service account uses wildcard/broad cloud permissions | M16: IaC rule for agent workload identity with wildcard actions/resources or broad predefined admin roles. | N16: Least-privilege role scoped to approved tools/resources | O16: N/A | P16: IAM roles/actions/resources with wildcard/admin/editor/owner | Q16: rules/builtin/authorization.yaml | R16: https://github.com/akarshkn17/AgentGuard/blob/main/rules/builtin/authorization.yaml | S16: IAM_03 (Least-Privilege Resource-Scoped IAM); IAM_12 (Periodic Access Review & Recertification); REG_04 (Policy-as-Code Coverage for Must Controls); SEC_15 (Agent Registry Compliance Gate); IR_01 (Multi-Level Kill-Switch Model)
A17: AIR-AUTH-005 | B17: Tool allowlist is derived from model or user input | C17: agentguard | D17: Native | E17: Authorization | F17: Critical | G17: taint | H17: agent, tool | I17: llm_output, user_input | J17: policy_mutation | K17: allowlist | L17: Tool allowlist is derived from model or user input | M17: Flag tainted values mutating enabled/allowed tool lists. | N17: Server-side static/policy-derived allowlist | O17: User/model-selected tool names | P17: enabled_tools/allowed_tools/tool registry | Q17: rules/builtin/authorization.yaml | R17: https://github.com/akarshkn17/AgentGuard/blob/main/rules/builtin/authorization.yaml | S17: SEC_06 (Structured Output Schema + Tool Name Auth); REG_02 (Agent Manifest Schema Validation); SEC_21 (Policy-as-Code for AI Controls); MON_04 (Tool Invocation Monitoring + Auto-Response); IR_01 (Multi-Level Kill-Switch Model)
A18: AIR-AUTH-006 | B18: All registered tools exposed to model regardless of user role | C18: agentguard | D18: Native | E18: Authorization | F18: High | G18: config | H18: agent | L18: All registered tools exposed to model regardless of user role | M18: Flag sensitive tool set bound unconditionally in apps with multiple roles/tenants. | N18: Role/policy-filtered tool set | O18: User role/identity | P18: llm.bind_tools/tools=[all_tools]/agent executor | Q18: rules/builtin/authorization.yaml | R18: https://github.com/akarshkn17/AgentGuard/blob/main/rules/builtin/authorization.yaml | S18: IAM_03 (Least-Privilege Resource-Scoped IAM); IAM_04 (User Identity Propagation - AgentAuthContext); REG_02 (Agent Manifest Schema Validation); SEC_15 (Agent Registry Compliance Gate)
A19: AIR-AUTH-007 | B19: Sensitive action lacks step-up or human approval gate | C19: agentguard | D19: Native | E19: Authorization | F19: Critical | G19: control_flow | H19: agent, tool | I19: llm_output | K19: approval_gate | L19: Sensitive action lacks step-up or human approval gate | M19: Flag configured high-impact sinks directly reachable from model tool call without approval function/node. | N19: Explicit approval/policy node | O19: LLM tool-call decision | P19: delete/deploy/payment/email/admin/production side-effect | Q19: rules/builtin/authorization.yaml | R19: https://github.com/akarshkn17/AgentGuard/blob/main/rules/builtin/authorization.yaml | S19: SEC_18 (Human-in-the-Loop for High-Risk Actions); BIZ_02 (High-Risk Action Catalog); IAM_11 (Conditional Access for Agent Admin Operations); MON_03 (Decision Trace Logging - Tool, Policy and Evidence Trace)
A20: AIR-AUTH-008 | B20: Authorization result cached without user/resource scoping | C20: agentguard | D20: Native | E20: Authorization | F20: High | G20: config | H20: tool | L20: Authorization result cached without user/resource scoping | M20: Flag global/static allow cache or cache keyed only by tool/action. | N20: Cache key includes principal, action, resource, policy version | O20: Auth decision cache | P20: tool/resource access | Q20: rules/builtin/authorization.yaml | R20: https://github.com/akarshkn17/AgentGuard/blob/main/rules/builtin/authorization.yaml | S20: IAM_04 (User Identity Propagation - AgentAuthContext); IAM_03 (Least-Privilege Resource-Scoped IAM); MON_03 (Decision Trace Logging - Tool, Policy and Evidence Trace)
A21: AIR-CLOUD-001 | B21: Agent service account key embedded or mounted as static credential | C21: agentguard | D21: Native | E21: Cloud Config | F21: Critical | G21: secret | H21: agent_runtime | I21: sensitive_data | L21: Agent service account key embedded or mounted as static credential | M21: Detect cloud key JSON/private key files and static credential mounts in agent deployments. | N21: Workload identity / short-lived credentials | O21: Service-account key file/token | P21: container/env/secret volume/code | Q21: rules/builtin/cloud_config.yaml | R21: https://github.com/akarshkn17/AgentGuard/blob/main/rules/builtin/cloud_config.yaml | S21: IAM_02 (Workload Identity - Zero Static Key Files); ENC_01 (Secrets Retrieval via Platform Module - No Bypass); IAM_09 (Non-Human Identity (NHI) Lifecycle Management); SEC_11 (CI/CD Gates - Secret Scan, SAST, Signed Skills, Pinned Models)
A22: AIR-CLOUD-002 | B22: Agent container runs privileged or with host mounts | C22: agentguard | D22: Native | E22: Cloud Config | F22: Critical | G22: config | H22: agent_runtime | K22: path_containment | L22: Agent container runs privileged or with host mounts | M22: Kubernetes/Docker IaC rule scoped to AI agent/tool/MCP workloads. | N22: Restricted container security context | O22: N/A | P22: privileged:true, hostPath, docker.sock, hostNetwork/hostPID | Q22: rules/builtin/cloud_config.yaml | R22: https://github.com/akarshkn17/AgentGuard/blob/main/rules/builtin/cloud_config.yaml | S22: IAM_03 (Least-Privilege Resource-Scoped IAM); SEC_11 (CI/CD Gates - Secret Scan, SAST, Signed Skills, Pinned Models); REG_04 (Policy-as-Code Coverage for Must Controls)
A23: AIR-CLOUD-003 | B23: Agent workload has unrestricted outbound network egress | C23: agentguard | D23: Native | E23: Cloud Config | F23: High | G23: config | H23: agent_runtime | K23: allowlist | L23: Agent workload has unrestricted outbound network egress | M23: Flag agent/tool workloads with powerful data access and no egress restrictions; repository-level config rule. | N23: Egress allowlist/proxy/network policy | O23: N/A | P23: no NetworkPolicy/egress restriction where architecture expects isolation | Q23: rules/builtin/cloud_config.yaml | R23: https://github.com/akarshkn17/AgentGuard/blob/main/rules/builtin/cloud_config.yaml | S23: NET_06 (Per-Agent Egress Allowlist); NET_11 (Network Segmentation by Trust Tier); NET_12 (Data Exfiltration Perimeter (Egress DLP)); MON_11 (Security Threat Detection Integration)
A24: AIR-CLOUD-004 | B24: Publicly exposed agent/MCP/admin service without auth proxy | C24: agentguard | D24: Native | E24: Cloud Config | F24: Critical | G24: config | H24: agent_runtime | L24: Publicly exposed agent/MCP/admin service without auth proxy | M24: Correlate public ingress with service lacking app/auth middleware. | N24: Auth gateway/IAP/API gateway/private ingress | O24: Internet ingress | P24: LoadBalancer/Ingress/public endpoint to sensitive service | Q24: rules/builtin/cloud_config.yaml | R24: https://github.com/akarshkn17/AgentGuard/blob/main/rules/builtin/cloud_config.yaml | S24: NET_01 (WAF-Capable Edge for Every Agent); NET_04 (Private Origin Configuration); MCP_02 (MCP Authentication and Authorization); NET_09 (Geo & IP Allowlisting)
A25: AIR-EXEC-001 | B25: LLM or user input reaches shell command execution | C25: agentguard | D25: Native | E25: Code Execution | F25: Critical | G25: taint | H25: tool, agent | I25: user_input, llm_output, tool_result, retrieval | J25: shell_execution | K25: allowlist | L25: LLM or user input reaches shell command execution | M25: Source-to-sink taint rule; treat string formatting into shell commands as exploitable. | N25: Argument arrays, allowlisted commands, no shell interpolation | O25: User input, model output, tool args, retrieved content | P25: os.system, subprocess.* with shell=True, child_process.exec, execSync, spawn with shell | Q25: rules/builtin/code_execution.yaml | R25: https://github.com/akarshkn17/AgentGuard/blob/main/rules/builtin/code_execution.yaml | S25: SEC_11 (CI/CD Gates - Secret Scan, SAST, Signed Skills, Pinned Models); MON_04 (Tool Invocation Monitoring + Auto-Response); SEC_06 (Structured Output Schema + Tool Name Auth); SEC_18 (Human-in-the-Loop for High-Risk Actions)
A26: AIR-EXEC-002 | B26: LLM or user input reaches eval/exec | C26: agentguard | D26: Native | E26: Code Execution | F26: Critical | G26: taint | H26: tool, agent | I26: user_input, llm_output, tool_result, retrieval | J26: dynamic_code | K26: allowlist | L26: LLM or user input reaches eval/exec | M26: Flag any untrusted source reaching dynamic language execution. | N26: No dynamic code execution; parser/allowlist instead | O26: User/model/tool/retrieval content | P26: eval, exec, compile+exec, Function(), vm.runIn* | Q26: rules/builtin/code_execution.yaml | R26: https://github.com/akarshkn17/AgentGuard/blob/main/rules/builtin/code_execution.yaml | S26: SEC_11 (CI/CD Gates - Secret Scan, SAST, Signed Skills, Pinned Models); MON_04 (Tool Invocation Monitoring + Auto-Response); SEC_06 (Structured Output Schema + Tool Name Auth); SEC_18 (Human-in-the-Loop for High-Risk Actions)
A27: AIR-EXEC-003 | B27: Dynamic import/module loading from untrusted input | C27: agentguard | D27: Native | E27: Code Execution | F27: High | G27: taint | H27: tool, agent | I27: llm_output, path_input, user_input | K27: allowlist | L27: Dynamic import/module loading from untrusted input | M27: Flag untrusted module/package name reaching dynamic import API. | N27: Allowlisted module identifiers | O27: User/model/tool-controlled module/package/path | P27: importlib.import_module, __import__, require(), dynamic import() | Q27: rules/builtin/code_execution.yaml | R27: https://github.com/akarshkn17/AgentGuard/blob/main/rules/builtin/code_execution.yaml | S27: SEC_11 (CI/CD Gates - Secret Scan, SAST, Signed Skills, Pinned Models); MON_04 (Tool Invocation Monitoring + Auto-Response); SEC_06 (Structured Output Schema + Tool Name Auth); SEC_18 (Human-in-the-Loop for High-Risk Actions)
A28: AIR-EXEC-004 | B28: LLM or user input reaches SQL query construction | C28: agentguard | D28: Native | E28: Injection | F28: Critical | G28: taint | H28: tool, agent | I28: user_input, llm_output | J28: sql_query | L28: LLM or user input reaches SQL query construction | M28: Flag tainted value concatenated/interpolated into SQL passed to execution sink. | N28: Parameterized queries / query builder | O28: User input, model output, tool args | P28: cursor.execute/query/raw SQL/string SQL APIs | Q28: rules/builtin/injection.yaml | R28: https://github.com/akarshkn17/AgentGuard/blob/main/rules/builtin/injection.yaml | S28: SEC_11 (CI/CD Gates - Secret Scan, SAST, Signed Skills, Pinned Models); MON_04 (Tool Invocation Monitoring + Auto-Response); SEC_06 (Structured Output Schema + Tool Name Auth); IR_01 (Multi-Level Kill-Switch Model)
A29: AIR-EXEC-005 | B29: LLM or user input reaches NoSQL/graph query object unsafely | C29: agentguard | D29: Native | E29: Injection | F29: High | G29: taint | H29: tool, agent | I29: llm_output, user_input | K29: allowlist, schema_validation | L29: LLM or user input reaches NoSQL/graph query object unsafely | M29: Flag tainted object/operator keys such as $where/$regex/script or raw graph query strings. | N29: Schema + operator allowlist; parameterized query APIs | O29: User/model/tool-controlled filters/operators | P29: Mongo find/update, Elasticsearch query DSL, Cypher/Gremlin raw query | Q29: rules/builtin/injection.yaml | R29: https://github.com/akarshkn17/AgentGuard/blob/main/rules/builtin/injection.yaml | S29: SEC_11 (CI/CD Gates - Secret Scan, SAST, Signed Skills, Pinned Models); MON_04 (Tool Invocation Monitoring + Auto-Response); SEC_06 (Structured Output Schema + Tool Name Auth)
A30: AIR-EXEC-006 | B30: LLM output reaches template engine with code-capable expressions | C30: agentguard | D30: Native | E30: Injection | F30: Critical | G30: taint | H30: tool, agent | I30: llm_output, user_input | L30: LLM output reaches template engine with code-capable expressions | M30: Flag untrusted content used as template source rather than template data. | N30: Sandboxed template + fixed template source | O30: Model/user/tool content | P30: Jinja2 Template/from_string, render_template_string, EJS/Pug/Handlebars unsafe helpers | Q30: rules/builtin/injection.yaml | R30: https://github.com/akarshkn17/AgentGuard/blob/main/rules/builtin/injection.yaml | S30: SEC_11 (CI/CD Gates - Secret Scan, SAST, Signed Skills, Pinned Models); MON_04 (Tool Invocation Monitoring + Auto-Response); SEC_06 (Structured Output Schema + Tool Name Auth); SEC_18 (Human-in-the-Loop for High-Risk Actions)
A31: AIR-EXEC-007 | B31: Downloaded content executed without integrity verification | C31: agentguard | D31: Native | E31: Code Execution | F31: Critical | G31: taint | H31: tool, skill | I31: url_input | J31: shell_execution | K31: signature_verification | L31: Downloaded content executed without integrity verification | M31: Detect download-to-execute chains and curl|bash / wget|sh patterns. | N31: Checksum/signature verification and trusted origin | O31: HTTP download, curl/wget, remote URL, package artifact | P31: shell execution, chmod+execute, python/node/bash invocation | Q31: rules/builtin/code_execution.yaml | R31: https://github.com/akarshkn17/AgentGuard/blob/main/rules/builtin/code_execution.yaml | S31: SEC_11 (CI/CD Gates - Secret Scan, SAST, Signed Skills, Pinned Models); MON_04 (Tool Invocation Monitoring + Auto-Response); SEC_20 (AIBOM - AI Bill of Materials); REG_03 (AIBOM Required for Every Agent); REG_05 (Agent Risk Tiering and Promotion Workflow); IR_01 (Multi-Level Kill-Switch Model)
A32: AIR-EXEC-008 | B32: Skill installs and executes unpinned package at runtime | C32: agentguard | D32: Native | E32: Code Execution | F32: High | G32: dependency | H32: skill, plugin | L32: Skill installs and executes unpinned package at runtime | M32: Flag pip install pkg, npm install pkg, npx pkg without exact version/digest inside skills/tools. | N32: Pinned version + lockfile + trusted registry | O32: pip/npm/uv/npx/package install command in skill/tool | P32: runtime execution/import of installed package | Q32: rules/builtin/code_execution.yaml | R32: https://github.com/akarshkn17/AgentGuard/blob/main/rules/builtin/code_execution.yaml | S32: SEC_11 (CI/CD Gates - Secret Scan, SAST, Signed Skills, Pinned Models); MON_04 (Tool Invocation Monitoring + Auto-Response); SEC_20 (AIBOM - AI Bill of Materials); REG_03 (AIBOM Required for Every Agent); REG_05 (Agent Risk Tiering and Promotion Workflow)
A33: AIR-EXEC-009 | B33: User or model-controlled interpreter selection | C33: agentguard | D33: Native | E33: Code Execution | F33: Critical | G33: taint | H33: tool | I33: path_input, user_input | J33: dynamic_code, shell_execution | K33: allowlist | L33: User or model-controlled interpreter selection | M33: Flag tainted executable/program argument at process-creation sink. | N33: Fixed executable allowlist | O33: Interpreter/runtime name or executable path from input | P33: subprocess/exec/spawn | Q33: rules/builtin/code_execution.yaml | R33: https://github.com/akarshkn17/AgentGuard/blob/main/rules/builtin/code_execution.yaml | S33: SEC_11 (CI/CD Gates - Secret Scan, SAST, Signed Skills, Pinned Models); MON_04 (Tool Invocation Monitoring + Auto-Response); SEC_06 (Structured Output Schema + Tool Name Auth); SEC_18 (Human-in-the-Loop for High-Risk Actions)
A34: AIR-FILE-001 | B34: Model-controlled path reaches file read | C34: agentguard | D34: Native | E34: File Access | F34: High | G34: taint | H34: tool, agent | I34: user_input, llm_output, path_input | J34: file_read | L34: Model-controlled path reaches file read | M34: Flag tainted path at read sink without resolve+root containment check. | N34: Canonicalize + restrict to approved root | O34: Model/user/tool path | P34: open/readFile/read_text/send_file/file loader | Q34: rules/builtin/file_access.yaml | R34: https://github.com/akarshkn17/AgentGuard/blob/main/rules/builtin/file_access.yaml | S34: SEC_11 (CI/CD Gates - Secret Scan, SAST, Signed Skills, Pinned Models); MON_04 (Tool Invocation Monitoring + Auto-Response)
A35: AIR-FILE-002 | B35: Model-controlled path reaches file write/delete | C35: agentguard | D35: Native | E35: File Access | F35: Critical | G35: taint | H35: tool, agent | I35: user_input, llm_output, path_input | J35: file_write | L35: Model-controlled path reaches file write/delete | M35: Flag tainted path at write/delete sink without containment policy. | N35: Canonicalize + approved writable root + deny sensitive paths | O35: Model/user/tool path | P35: open(write), writeFile, unlink/remove/rmtree, rename | Q35: rules/builtin/file_access.yaml | R35: https://github.com/akarshkn17/AgentGuard/blob/main/rules/builtin/file_access.yaml | S35: SEC_11 (CI/CD Gates - Secret Scan, SAST, Signed Skills, Pinned Models); SEC_18 (Human-in-the-Loop for High-Risk Actions); MON_04 (Tool Invocation Monitoring + Auto-Response)
A36: AIR-FILE-003 | B36: Arbitrary local URI loader permits file disclosure | C36: agentguard | D36: Native | E36: File Access | F36: High | G36: taint | H36: tool, rag | I36: llm_output, url_input, user_input | J36: file_read | K36: allowlist | L36: Arbitrary local URI loader permits file disclosure | M36: Flag user/model URI entering loader that supports file:// or local paths. | N36: Allowlisted schemes and roots | O36: User/model-controlled URI | P36: file:// loader, generic URL/file loader, document loader | Q36: rules/builtin/file_access.yaml | R36: https://github.com/akarshkn17/AgentGuard/blob/main/rules/builtin/file_access.yaml | S36: SEC_11 (CI/CD Gates - Secret Scan, SAST, Signed Skills, Pinned Models); MON_04 (Tool Invocation Monitoring + Auto-Response)
A37: AIR-FILE-004 | B37: Unsafe archive extraction permits Zip Slip | C37: agentguard | D37: Native | E37: Archive | F37: High | G37: taint | H37: tool, skill | L37: Unsafe archive extraction permits Zip Slip | M37: Flag archive extraction without member path containment validation. | N37: Validate each extracted path remains under destination | O37: Uploaded/downloaded archive | P37: extractall/unzip/tar extraction | Q37: rules/builtin/archive.yaml | R37: https://github.com/akarshkn17/AgentGuard/blob/main/rules/builtin/archive.yaml | S37: SEC_11 (CI/CD Gates - Secret Scan, SAST, Signed Skills, Pinned Models); MON_04 (Tool Invocation Monitoring + Auto-Response)
A38: AIR-FILE-005 | B38: Uploaded executable/script content stored in executable location | C38: agentguard | D38: Native | E38: File Upload | F38: Critical | G38: taint | H38: tool, agent | I38: retrieval | L38: Uploaded executable/script content stored in executable location | M38: Flag uploads written into directories later imported/executed or served as executable content. | N38: Extension/content validation + non-executable storage | O38: User/tool file upload | P38: web root, plugin/skill directory, executable workspace | Q38: rules/builtin/file_upload.yaml | R38: https://github.com/akarshkn17/AgentGuard/blob/main/rules/builtin/file_upload.yaml | S38: SEC_11 (CI/CD Gates - Secret Scan, SAST, Signed Skills, Pinned Models); SEC_10 (Document Screening for File-Typed Outputs); MON_04 (Tool Invocation Monitoring + Auto-Response); IR_01 (Multi-Level Kill-Switch Model)
A39: AIR-FILE-006 | B39: Skill scans broad filesystem or home directory for secrets | C39: agentguard | D39: Native | E39: File Access | F39: High | G39: structural | H39: skill, agent | K39: allowlist | L39: Skill scans broad filesystem or home directory for secrets | M39: Flag skill/tool instructions or code that enumerate known credential paths without a narrow documented target. | N39: Explicit narrow file allowlist | O39: Skill/tool logic | P39: ~/.ssh, ~/.aws, ~/.config, .env, credentials files, recursive home scan | Q39: rules/builtin/file_access.yaml | R39: https://github.com/akarshkn17/AgentGuard/blob/main/rules/builtin/file_access.yaml | S39: SEC_11 (CI/CD Gates - Secret Scan, SAST, Signed Skills, Pinned Models); ENC_01 (Secrets Retrieval via Platform Module - No Bypass); DATA_03 (DLP at Prompt Assembly Time); MON_04 (Tool Invocation Monitoring + Auto-Response)
A40: AIR-MCP-001 | B40: MCP server exposed over plaintext HTTP | C40: agentguard | D40: Native | E40: MCP | F40: High | G40: config | H40: mcp_server | K40: tls_validation | L40: MCP server exposed over plaintext HTTP | M40: Flag network MCP server configured with plaintext remote listener; exempt loopback/local development by policy. | N40: TLS or trusted local-only transport | O40: N/A | P40: http:// listener / SSE or streamable HTTP without TLS termination requirement | Q40: rules/builtin/mcp.yaml | R40: https://github.com/akarshkn17/AgentGuard/blob/main/rules/builtin/mcp.yaml | S40: NET_03 (TLS 1.2+ End-to-End); MCP_01 (Approved MCP Server Registry); SEC_22 (Formal MCP Server Security Review); MCP_04 (MCP Network Isolation and Egress Control)
A41: AIR-MCP-002 | B41: MCP server lacks authentication for sensitive tools/resources | C41: agentguard | D41: Native | E41: MCP | F41: Critical | G41: control_flow | H41: mcp_server | I41: user_input | K41: authorization_check | L41: MCP server lacks authentication for sensitive tools/resources | M41: Flag sensitive handlers reachable without auth middleware/decorator or identity check. | N41: OAuth/workload identity/API auth plus authorization | O41: Incoming MCP request | P41: tool/resource/prompt handler | Q41: rules/builtin/mcp.yaml | R41: https://github.com/akarshkn17/AgentGuard/blob/main/rules/builtin/mcp.yaml | S41: MCP_02 (MCP Authentication and Authorization); MCP_01 (Approved MCP Server Registry); SEC_22 (Formal MCP Server Security Review); IAM_03 (Least-Privilege Resource-Scoped IAM); MON_04 (Tool Invocation Monitoring + Auto-Response); IR_01 (Multi-Level Kill-Switch Model)
A42: AIR-MCP-003 | B42: MCP server trusts static shared token embedded in code/config | C42: agentguard | D42: Native | E42: MCP | F42: High | G42: secret | H42: mcp_server | I42: sensitive_data | L42: MCP server trusts static shared token embedded in code/config | M42: Secret-scan tokens specifically in MCP auth/server configuration. | N42: External secret store + rotation | O42: Hardcoded bearer/API token | P42: MCP authentication middleware | Q42: rules/builtin/mcp.yaml | R42: https://github.com/akarshkn17/AgentGuard/blob/main/rules/builtin/mcp.yaml | S42: ENC_01 (Secrets Retrieval via Platform Module - No Bypass); MCP_01 (Approved MCP Server Registry); SEC_22 (Formal MCP Server Security Review); IAM_08 (Short-Lived Token Enforcement); MCP_02 (MCP Authentication and Authorization); SEC_11 (CI/CD Gates - Secret Scan, SAST, Signed Skills, Pinned Models)
A43: AIR-MCP-004 | B43: Permissive CORS or missing Origin validation on browser-reachable MCP | C43: agentguard | D43: Native | E43: MCP | F43: High | G43: config | H43: mcp_server | L43: Permissive CORS or missing Origin validation on browser-reachable MCP | M43: Flag Access-Control-Allow-Origin:* or disabled origin checks on MCP network endpoints. | N43: Explicit trusted origins and origin validation | O43: Browser Origin | P43: MCP HTTP/SSE endpoint | Q43: rules/builtin/mcp.yaml | R43: https://github.com/akarshkn17/AgentGuard/blob/main/rules/builtin/mcp.yaml | S43: MCP_01 (Approved MCP Server Registry); SEC_22 (Formal MCP Server Security Review); NET_01 (WAF-Capable Edge for Every Agent); MCP_02 (MCP Authentication and Authorization)
A44: AIR-MCP-005 | B44: MCP server URL is user/model controlled | C44: agentguard | D44: Native | E44: MCP | F44: Critical | G44: taint | H44: mcp_client | K44: allowlist | L44: MCP server URL is user/model controlled | M44: Flag tainted server URL passed to MCP client connection. | N44: Server registry allowlist + fixed trust configuration | O44: User/model/config input at runtime | P44: MCP client connect/server URL | Q44: rules/builtin/mcp.yaml | R44: https://github.com/akarshkn17/AgentGuard/blob/main/rules/builtin/mcp.yaml | S44: MCP_01 (Approved MCP Server Registry); SEC_22 (Formal MCP Server Security Review); MCP_04 (MCP Network Isolation and Egress Control); NET_06 (Per-Agent Egress Allowlist); MCP_03 (MCP Schema and Argument Validation); IR_01 (Multi-Level Kill-Switch Model)
A45: AIR-MCP-006 | B45: Automatic trust of all discovered MCP tools | C45: agentguard | D45: Native | E45: MCP | F45: Critical | G45: config | H45: mcp_client | J45: policy_mutation | K45: allowlist, approval_gate | L45: Automatic trust of all discovered MCP tools | M45: Flag code that registers every remote tool in returned capability list without filtering. | N45: Per-server and per-tool allowlist/approval | O45: Remote list_tools/capabilities result | P45: agent tool registry | Q45: rules/builtin/mcp.yaml | R45: https://github.com/akarshkn17/AgentGuard/blob/main/rules/builtin/mcp.yaml | S45: MCP_01 (Approved MCP Server Registry); SEC_22 (Formal MCP Server Security Review); MCP_08 (MCP Periodic Recertification); REG_02 (Agent Manifest Schema Validation); SEC_15 (Agent Registry Compliance Gate); IR_01 (Multi-Level Kill-Switch Model)
A46: AIR-MCP-007 | B46: Remote MCP prompt inserted as system/developer message | C46: agentguard | D46: Native | E46: MCP | F46: Critical | G46: taint | H46: mcp_client | J46: privileged_prompt | L46: Remote MCP prompt inserted as system/developer message | M46: Flag remote MCP prompt content promoted to privileged message role. | N46: Treat remote prompt as untrusted content unless signed/approved | O46: MCP prompts/get or remote prompt content | P46: system/developer role | Q46: rules/builtin/mcp.yaml | R46: https://github.com/akarshkn17/AgentGuard/blob/main/rules/builtin/mcp.yaml | S46: MCP_05 (MCP Output Scanning and Boundary Tagging); SEC_03 (Indirect Injection Defense - Tool Output Sanitisation); MCP_01 (Approved MCP Server Registry); SEC_22 (Formal MCP Server Security Review); ENC_06 (System Prompt Integrity Protection); IR_01 (Multi-Level Kill-Switch Model)
A47: AIR-MCP-008 | B47: MCP resource URI permits path traversal | C47: agentguard | D47: Native | E47: MCP | F47: Critical | G47: taint | H47: mcp_server | I47: path_input, url_input | J47: file_read | K47: path_containment | L47: MCP resource URI permits path traversal | M47: Flag resource URI/path reaching filesystem sink without containment check. | N47: Canonical path + resource-root containment | O47: Resource URI/path parameter | P47: filesystem read/write/resource handler | Q47: rules/builtin/mcp.yaml | R47: https://github.com/akarshkn17/AgentGuard/blob/main/rules/builtin/mcp.yaml | S47: MCP_01 (Approved MCP Server Registry); SEC_22 (Formal MCP Server Security Review); MCP_03 (MCP Schema and Argument Validation); IR_01 (Multi-Level Kill-Switch Model)
A48: AIR-MCP-009 | B48: MCP resource handler permits arbitrary URL fetching | C48: agentguard | D48: Native | E48: MCP | F48: Critical | G48: taint | H48: mcp_server | I48: url_input, user_input | K48: allowlist | L48: MCP resource handler permits arbitrary URL fetching | M48: Flag resource/tool parameters used as arbitrary outbound URL. | N48: Scheme/host allowlist + SSRF protections | O48: Resource URI or tool argument | P48: HTTP fetch/client | Q48: rules/builtin/mcp.yaml | R48: https://github.com/akarshkn17/AgentGuard/blob/main/rules/builtin/mcp.yaml | S48: MCP_01 (Approved MCP Server Registry); SEC_22 (Formal MCP Server Security Review); MCP_04 (MCP Network Isolation and Egress Control); NET_06 (Per-Agent Egress Allowlist); IR_01 (Multi-Level Kill-Switch Model)
A49: AIR-MCP-010 | B49: MCP tool exposes arbitrary command execution primitive | C49: agentguard | D49: Native | E49: MCP | F49: Critical | G49: taint | H49: mcp_server | I49: user_input, llm_output | J49: shell_execution | K49: allowlist, schema_validation | L49: MCP tool exposes arbitrary command execution primitive | M49: Flag MCP tools whose user/model-controlled schema is directly mapped to process execution. | N49: Narrow task-specific tool schema and command allowlist | O49: Tool schema fields such as command, cmd, shell, script | P49: process execution APIs | Q49: rules/builtin/mcp.yaml | R49: https://github.com/akarshkn17/AgentGuard/blob/main/rules/builtin/mcp.yaml | S49: MCP_01 (Approved MCP Server Registry); SEC_22 (Formal MCP Server Security Review); MCP_03 (MCP Schema and Argument Validation); SEC_18 (Human-in-the-Loop for High-Risk Actions)
A50: AIR-MCP-011 | B50: MCP tool exposes arbitrary filesystem primitive | C50: agentguard | D50: Native | E50: MCP | F50: High | G50: taint | H50: mcp_server | I50: user_input, llm_output, path_input | J50: file_read, file_write | K50: allowlist | L50: MCP tool exposes arbitrary filesystem primitive | M50: Flag generic read/write/delete tools accepting arbitrary paths without root restriction. | N50: Scoped root + operation allowlist | O50: Tool schema fields path/file/directory | P50: read/write/delete filesystem APIs | Q50: rules/builtin/mcp.yaml | R50: https://github.com/akarshkn17/AgentGuard/blob/main/rules/builtin/mcp.yaml | S50: MCP_01 (Approved MCP Server Registry); SEC_22 (Formal MCP Server Security Review); MCP_03 (MCP Schema and Argument Validation); SEC_18 (Human-in-the-Loop for High-Risk Actions)
A51: AIR-MCP-012 | B51: MCP tool exposes arbitrary HTTP request primitive | C51: agentguard | D51: Native | E51: MCP | F51: Critical | G51: taint | H51: mcp_server | I51: user_input, llm_output, url_input | J51: network_request | L51: MCP tool exposes arbitrary HTTP request primitive | M51: Flag generic request tools that forward model-controlled URL/method/headers. | N51: Approved domains/methods; SSRF and header restrictions | O51: Tool schema url/method/headers/body | P51: generic HTTP client | Q51: rules/builtin/mcp.yaml | R51: https://github.com/akarshkn17/AgentGuard/blob/main/rules/builtin/mcp.yaml | S51: MCP_01 (Approved MCP Server Registry); SEC_22 (Formal MCP Server Security Review); MCP_04 (MCP Network Isolation and Egress Control); NET_06 (Per-Agent Egress Allowlist); IR_01 (Multi-Level Kill-Switch Model)
A52: AIR-MCP-013 | B52: MCP tool result bypasses trust validation before sensitive action | C52: agentguard | D52: Native | E52: MCP | F52: High | G52: taint | H52: mcp_client | I52: mcp_result, tool_result | J52: network_request | K52: schema_validation | L52: MCP tool result bypasses trust validation before sensitive action | M52: Flag MCP result transitively reaching sensitive sink without validator/policy node. | N52: Schema and semantic validation; policy check | O52: MCP tool result | P52: privileged tool/action, command, query, file/network sink | Q52: rules/builtin/mcp.yaml | R52: https://github.com/akarshkn17/AgentGuard/blob/main/rules/builtin/mcp.yaml | S52: MCP_05 (MCP Output Scanning and Boundary Tagging); SEC_03 (Indirect Injection Defense - Tool Output Sanitisation); MCP_01 (Approved MCP Server Registry); SEC_22 (Formal MCP Server Security Review); MON_04 (Tool Invocation Monitoring + Auto-Response)
A53: AIR-MCP-014 | B53: MCP process launched through shell with interpolated configuration | C53: agentguard | D53: Native | E53: MCP | F53: Critical | G53: taint | H53: mcp_server | I53: user_input | J53: dynamic_code | L53: MCP process launched through shell with interpolated configuration | M53: Flag MCP stdio server launch using shell strings or interpolation. | N53: Direct argv process launch; fixed executable | O53: Server command/args/env from config or input | P53: shell=True, exec(command string) | Q53: rules/builtin/mcp.yaml | R53: https://github.com/akarshkn17/AgentGuard/blob/main/rules/builtin/mcp.yaml | S53: MCP_01 (Approved MCP Server Registry); SEC_22 (Formal MCP Server Security Review); MCP_03 (MCP Schema and Argument Validation); SEC_18 (Human-in-the-Loop for High-Risk Actions)
A54: AIR-MCP-015 | B54: Secrets stored directly in MCP configuration | C54: agentguard | D54: Native | E54: MCP | F54: Critical | G54: secret | H54: mcp_config | L54: Secrets stored directly in MCP configuration | M54: Secret scan MCP configuration and manifests. | N54: Secret references/environment injection from secret manager | O54: Tokens/passwords/API keys/private keys | P54: mcp.json, servers config, environment blocks, manifests | Q54: rules/builtin/mcp.yaml | R54: https://github.com/akarshkn17/AgentGuard/blob/main/rules/builtin/mcp.yaml | S54: ENC_01 (Secrets Retrieval via Platform Module - No Bypass); MCP_01 (Approved MCP Server Registry); SEC_22 (Formal MCP Server Security Review); SEC_11 (CI/CD Gates - Secret Scan, SAST, Signed Skills, Pinned Models); MCP_08 (MCP Periodic Recertification); IR_01 (Multi-Level Kill-Switch Model)
A55: AIR-MCP-016 | B55: MCP capability expansion is not bounded by configured policy | C55: agentguard | D55: Native | E55: MCP | F55: High | G55: config | H55: mcp_client | L55: MCP capability expansion is not bounded by configured policy | M55: Flag dynamic capability registration when no local allowlist/policy filter exists. | N55: Explicit configured capabilities per server | O55: Remote capability list | P55: agent available tools/resources/prompts | Q55: rules/builtin/mcp.yaml | R55: https://github.com/akarshkn17/AgentGuard/blob/main/rules/builtin/mcp.yaml | S55: MCP_01 (Approved MCP Server Registry); SEC_22 (Formal MCP Server Security Review); MCP_03 (MCP Schema and Argument Validation); REG_02 (Agent Manifest Schema Validation); SEC_21 (Policy-as-Code for AI Controls); REG_07 (Runtime Drift Detection Against Registry)
A56: AIR-MODEL-001 | B56: Remote model code execution enabled | C56: agentguard | D56: Native | E56: Model Supply Chain | F56: Critical | G56: config | H56: model_loader | L56: Remote model code execution enabled | M56: Direct rule for trust_remote_code=True and equivalent flags. | N56: Disable remote code or pin+review trusted repository | O56: N/A | P56: trust_remote_code=True or equivalent custom-code loading | Q56: rules/builtin/model_supply_chain.yaml | R56: https://github.com/akarshkn17/AgentGuard/blob/main/rules/builtin/model_supply_chain.yaml | S56: SEC_20 (AIBOM - AI Bill of Materials); REG_03 (AIBOM Required for Every Agent); REG_05 (Agent Risk Tiering and Promotion Workflow); SEC_11 (CI/CD Gates - Secret Scan, SAST, Signed Skills, Pinned Models)
A57: AIR-MODEL-002 | B57: Unsafe pickle/joblib model deserialization | C57: agentguard | D57: Native | E57: Model Supply Chain | F57: Critical | G57: taint | H57: model_loader | I57: user_input | J57: model_load | L57: Unsafe pickle/joblib model deserialization | M57: Flag untrusted artifact reaching unsafe deserialization. | N57: Safe format or cryptographically trusted artifact | O57: Downloaded/user-controlled model artifact | P57: pickle.load/loads, joblib.load, dill/cloudpickle | Q57: rules/builtin/model_supply_chain.yaml | R57: https://github.com/akarshkn17/AgentGuard/blob/main/rules/builtin/model_supply_chain.yaml | S57: SEC_20 (AIBOM - AI Bill of Materials); REG_03 (AIBOM Required for Every Agent); REG_05 (Agent Risk Tiering and Promotion Workflow); SEC_11 (CI/CD Gates - Secret Scan, SAST, Signed Skills, Pinned Models)
A58: AIR-MODEL-003 | B58: Unsafe torch.load of untrusted artifact | C58: agentguard | D58: Native | E58: Model Supply Chain | F58: Critical | G58: taint | H58: pytorch_model_loader | I58: user_input | J58: model_load | L58: Unsafe torch.load of untrusted artifact | M58: Flag untrusted path to torch.load; increase confidence when weights_only=False. | N58: weights_only=True plus trusted artifact policy | O58: Downloaded/user-controlled .pt/.pth artifact | P58: torch.load with weights_only=False/omitted where unsafe | Q58: rules/builtin/model_supply_chain.yaml | R58: https://github.com/akarshkn17/AgentGuard/blob/main/rules/builtin/model_supply_chain.yaml | S58: SEC_20 (AIBOM - AI Bill of Materials); REG_03 (AIBOM Required for Every Agent); REG_05 (Agent Risk Tiering and Promotion Workflow); SEC_11 (CI/CD Gates - Secret Scan, SAST, Signed Skills, Pinned Models)
A59: AIR-MODEL-004 | B59: Model revision/version is floating or unpinned | C59: agentguard | D59: Native | E59: Model Supply Chain | F59: High | G59: dependency | H59: model_loader | J59: model_load | L59: Model revision/version is floating or unpinned | M59: Flag production model loads without revision/version/digest pinning. | N59: Pinned immutable revision/digest | O59: N/A | P59: from_pretrained/model load using latest/main/master/no revision | Q59: rules/builtin/model_supply_chain.yaml | R59: https://github.com/akarshkn17/AgentGuard/blob/main/rules/builtin/model_supply_chain.yaml | S59: SEC_20 (AIBOM - AI Bill of Materials); REG_03 (AIBOM Required for Every Agent); REG_05 (Agent Risk Tiering and Promotion Workflow); SEC_11 (CI/CD Gates - Secret Scan, SAST, Signed Skills, Pinned Models)
A60: AIR-MODEL-005 | B60: LoRA/adapter loaded from untrusted or mutable source | C60: agentguard | D60: Native | E60: Model Supply Chain | F60: High | G60: taint | H60: model, adapter_loader | J60: model_load | L60: LoRA/adapter loaded from untrusted or mutable source | M60: Flag tainted adapter identifier or missing revision/digest. | N60: Trusted registry + pinned revision | O60: User/config remote adapter identifier | P60: adapter/PEFT load | Q60: rules/builtin/model_supply_chain.yaml | R60: https://github.com/akarshkn17/AgentGuard/blob/main/rules/builtin/model_supply_chain.yaml | S60: SEC_20 (AIBOM - AI Bill of Materials); REG_03 (AIBOM Required for Every Agent); REG_05 (Agent Risk Tiering and Promotion Workflow); SEC_11 (CI/CD Gates - Secret Scan, SAST, Signed Skills, Pinned Models)
A61: AIR-MODEL-006 | B61: Model/artifact downloaded without checksum or signature verification | C61: agentguard | D61: Native | E61: Model Supply Chain | F61: Critical | G61: taint | H61: artifact_downloader | I61: url_input | J61: model_load | K61: signature_verification | L61: Model/artifact downloaded without checksum or signature verification | M61: Detect remote download -> load chain without intervening integrity verification. | N61: Digest/signature verification before load | O61: Remote URL | P61: model load/deserialization | Q61: rules/builtin/model_supply_chain.yaml | R61: https://github.com/akarshkn17/AgentGuard/blob/main/rules/builtin/model_supply_chain.yaml | S61: SEC_20 (AIBOM - AI Bill of Materials); REG_03 (AIBOM Required for Every Agent); REG_05 (Agent Risk Tiering and Promotion Workflow); SEC_11 (CI/CD Gates - Secret Scan, SAST, Signed Skills, Pinned Models)
A62: AIR-MODEL-007 | B62: Model API base URL is user/model controlled | C62: agentguard | D62: Native | E62: Model Provider | F62: Critical | G62: taint | H62: llm_client | K62: allowlist | L62: Model API base URL is user/model controlled | M62: Flag tainted endpoint/base_url passed to LLM/embedding client. | N62: Provider allowlist | O62: Request/model/config runtime input | P62: OpenAI-compatible base_url/endpoint/client host | Q62: rules/builtin/model_provider.yaml | R62: https://github.com/akarshkn17/AgentGuard/blob/main/rules/builtin/model_provider.yaml | S62: SEC_20 (AIBOM - AI Bill of Materials); REG_03 (AIBOM Required for Every Agent); REG_05 (Agent Risk Tiering and Promotion Workflow); SEC_11 (CI/CD Gates - Secret Scan, SAST, Signed Skills, Pinned Models); NET_06 (Per-Agent Egress Allowlist)
A63: AIR-MODEL-008 | B63: Unapproved model identifier is user/model controlled | C63: agentguard | D63: Native | E63: Model Provider | F63: High | G63: taint | H63: llm_client | K63: allowlist | L63: Unapproved model identifier is user/model controlled | M63: Flag tainted model name when no explicit allowlist check dominates. | N63: Approved model allowlist | O63: Request/model-selected model name | P63: LLM client model parameter | Q63: rules/builtin/model_provider.yaml | R63: https://github.com/akarshkn17/AgentGuard/blob/main/rules/builtin/model_provider.yaml | S63: REG_02 (Agent Manifest Schema Validation); SEC_20 (AIBOM - AI Bill of Materials); REG_03 (AIBOM Required for Every Agent); REG_05 (Agent Risk Tiering and Promotion Workflow); SEC_11 (CI/CD Gates - Secret Scan, SAST, Signed Skills, Pinned Models); SEC_15 (Agent Registry Compliance Gate)
A64: AIR-MODEL-009 | B64: User-controlled local model path | C64: agentguard | D64: Native | E64: Model Supply Chain | F64: High | G64: taint | H64: model_loader | I64: path_input, user_input | J64: model_load | K64: path_containment | L64: User-controlled local model path | M64: Flag tainted path passed to model/tokenizer loader. | N64: Trusted model directory + canonical containment | O64: Request/model file path | P64: model/tokenizer/adapter loader | Q64: rules/builtin/model_supply_chain.yaml | R64: https://github.com/akarshkn17/AgentGuard/blob/main/rules/builtin/model_supply_chain.yaml | S64: SEC_20 (AIBOM - AI Bill of Materials); REG_03 (AIBOM Required for Every Agent); REG_05 (Agent Risk Tiering and Promotion Workflow); SEC_11 (CI/CD Gates - Secret Scan, SAST, Signed Skills, Pinned Models)
A65: AIR-MODEL-010 | B65: Provider client configured with TLS verification disabled | C65: agentguard | D65: Native | E65: Model Provider | F65: High | G65: config | H65: llm_client | J65: network_request | K65: tls_validation | L65: Provider client configured with TLS verification disabled | M65: Direct pattern on model/embedding provider HTTP configuration. | N65: TLS verification enabled | O65: N/A | P65: custom HTTP client verify=False / insecure transport | Q65: rules/builtin/model_provider.yaml | R65: https://github.com/akarshkn17/AgentGuard/blob/main/rules/builtin/model_provider.yaml | S65: NET_03 (TLS 1.2+ End-to-End); SEC_20 (AIBOM - AI Bill of Materials); REG_03 (AIBOM Required for Every Agent); REG_05 (Agent Risk Tiering and Promotion Workflow); SEC_11 (CI/CD Gates - Secret Scan, SAST, Signed Skills, Pinned Models)
A66: AIR-NET-001 | B66: Model-controlled URL reaches HTTP client without SSRF protection | C66: agentguard | D66: Native | E66: Network | F66: Critical | G66: taint | H66: tool, agent | I66: user_input, llm_output, url_input | J66: network_request | K66: allowlist | L66: Model-controlled URL reaches HTTP client without SSRF protection | M66: Flag tainted URL reaching outbound HTTP client when no URL validator/allowlist dominates. | N66: Scheme/host allowlist; block private/link-local/metadata IPs; re-resolve DNS | O66: LLM output, tool args, user input, retrieved URL | P66: requests/httpx/urllib/fetch/axios/got/http client | Q66: rules/builtin/network.yaml | R66: https://github.com/akarshkn17/AgentGuard/blob/main/rules/builtin/network.yaml | S66: NET_06 (Per-Agent Egress Allowlist); NET_07 (Private Connectivity to Managed Platform Services); NET_12 (Data Exfiltration Perimeter (Egress DLP)); MON_04 (Tool Invocation Monitoring + Auto-Response); IR_01 (Multi-Level Kill-Switch Model)
A67: AIR-NET-002 | B67: Arbitrary webhook/callback destination controlled by model | C67: agentguard | D67: Native | E67: Network | F67: High | G67: taint | H67: tool, agent | K67: allowlist | L67: Arbitrary webhook/callback destination controlled by model | M67: Flag model/user URL used for callbacks/webhooks without registered destination check. | N67: Registered destination allowlist | O67: Model/user-provided webhook/callback URL | P67: HTTP POST/client sink | Q67: rules/builtin/network.yaml | R67: https://github.com/akarshkn17/AgentGuard/blob/main/rules/builtin/network.yaml | S67: NET_06 (Per-Agent Egress Allowlist); NET_07 (Private Connectivity to Managed Platform Services); NET_12 (Data Exfiltration Perimeter (Egress DLP)); MON_04 (Tool Invocation Monitoring + Auto-Response)
A68: AIR-NET-003 | B68: Sensitive data sent to arbitrary external endpoint | C68: agentguard | D68: Native | E68: Data Exfiltration | F68: Critical | G68: taint | H68: agent, tool, skill | I68: sensitive_data | J68: network_request | K68: allowlist, redaction | L68: Sensitive data sent to arbitrary external endpoint | M68: Sensitive-source-to-network-sink taint rule; raise when destination is dynamic or external. | N68: Approved-domain allowlist + DLP/redaction | O68: Secrets, PII, files, env vars, retrieval context | P68: HTTP/email/webhook/socket upload | Q68: rules/builtin/data_exfiltration.yaml | R68: https://github.com/akarshkn17/AgentGuard/blob/main/rules/builtin/data_exfiltration.yaml | S68: NET_12 (Data Exfiltration Perimeter (Egress DLP)); NET_06 (Per-Agent Egress Allowlist); DATA_03 (DLP at Prompt Assembly Time); DATA_02 (PII Handling, Redaction, Pseudonymisation); MON_04 (Tool Invocation Monitoring + Auto-Response); IR_01 (Multi-Level Kill-Switch Model)
A69: AIR-NET-004 | B69: TLS certificate verification disabled | C69: agentguard | D69: Native | E69: TLS | F69: High | G69: config | H69: agent, mcp, tool | K69: tls_validation | L69: TLS certificate verification disabled | M69: Direct pattern/config rule in AI agents, MCP clients/servers, tools and model-provider clients. | N69: TLS verification enabled | O69: N/A | P69: verify=False, rejectUnauthorized:false, NODE_TLS_REJECT_UNAUTHORIZED=0, insecure transport option | Q69: rules/builtin/tls.yaml | R69: https://github.com/akarshkn17/AgentGuard/blob/main/rules/builtin/tls.yaml | S69: NET_03 (TLS 1.2+ End-to-End); NET_10 (DNS & Certificate Governance)
A70: AIR-NET-005 | B70: Proxy configuration allows untrusted proxy injection | C70: agentguard | D70: Native | E70: Network | F70: High | G70: taint | H70: agent, tool | K70: allowlist | L70: Proxy configuration allows untrusted proxy injection | M70: Flag tainted proxy configuration that can intercept model/tool traffic. | N70: Trusted fixed proxy or allowlist | O70: User/model/environment-controlled proxy URL | P70: HTTP client proxy setting | Q70: rules/builtin/network.yaml | R70: https://github.com/akarshkn17/AgentGuard/blob/main/rules/builtin/network.yaml | S70: NET_06 (Per-Agent Egress Allowlist); NET_10 (DNS & Certificate Governance)
A71: AIR-NET-006 | B71: Internal cloud metadata endpoint reachable from generic fetch tool | C71: agentguard | D71: Native | E71: Network | F71: Critical | G71: taint | H71: tool | I71: url_input | L71: Internal cloud metadata endpoint reachable from generic fetch tool | M71: Flag generic HTTP tools lacking private/link-local denial or containing direct metadata endpoint access. | N71: Explicit metadata/private-network denylist | O71: Generic fetch/browser/tool URL parameter | P71: 169.254.169.254, metadata.google.internal, metadata.azure, link-local ranges | Q71: rules/builtin/network.yaml | R71: https://github.com/akarshkn17/AgentGuard/blob/main/rules/builtin/network.yaml | S71: NET_06 (Per-Agent Egress Allowlist); NET_07 (Private Connectivity to Managed Platform Services); NET_12 (Data Exfiltration Perimeter (Egress DLP)); MON_04 (Tool Invocation Monitoring + Auto-Response); IR_01 (Multi-Level Kill-Switch Model)
A72: AIR-OUT-001 | B72: LLM-generated URL used without validation | C72: agentguard | D72: Native | E72: Output Validation | F72: Critical | G72: taint | H72: agent, tool | I72: llm_output | J72: network_request | K72: allowlist | L72: LLM-generated URL used without validation | M72: Model-output-to-HTTP sink rule with no validator. | N72: URL parser + scheme/host allowlist + SSRF controls | O72: LLM output | P72: browser/fetch/webhook/download | Q72: rules/builtin/output_validation.yaml | R72: https://github.com/akarshkn17/AgentGuard/blob/main/rules/builtin/output_validation.yaml | S72: SEC_09 (Malicious URL Detection in Tool Outputs); SEC_06 (Structured Output Schema + Tool Name Auth); SEC_05 (Output Content Scanning); IR_01 (Multi-Level Kill-Switch Model)
A73: AIR-OUT-002 | B73: LLM-generated file path used without validation | C73: agentguard | D73: Native | E73: Output Validation | F73: Critical | G73: taint | H73: agent, tool | I73: llm_output | J73: file_read, file_write | K73: path_containment | L73: LLM-generated file path used without validation | M73: Model-output-to-filesystem sink rule with no path guard. | N73: Canonical path and root containment | O73: LLM output | P73: file read/write/delete/load | Q73: rules/builtin/output_validation.yaml | R73: https://github.com/akarshkn17/AgentGuard/blob/main/rules/builtin/output_validation.yaml | S73: SEC_06 (Structured Output Schema + Tool Name Auth); SEC_05 (Output Content Scanning); IR_01 (Multi-Level Kill-Switch Model)
A74: AIR-OUT-003 | B74: LLM-generated command executed | C74: agentguard | D74: Native | E74: Output Validation | F74: Critical | G74: taint | H74: agent, tool | I74: llm_output | J74: shell_execution | K74: allowlist | L74: LLM-generated command executed | M74: Direct model-output-to-command-sink taint rule. | N74: No free-form command execution; structured allowlisted actions | O74: LLM output | P74: shell/process execution | Q74: rules/builtin/output_validation.yaml | R74: https://github.com/akarshkn17/AgentGuard/blob/main/rules/builtin/output_validation.yaml | S74: SEC_06 (Structured Output Schema + Tool Name Auth); SEC_18 (Human-in-the-Loop for High-Risk Actions); SEC_05 (Output Content Scanning)
A75: AIR-OUT-004 | B75: LLM-generated code executed | C75: agentguard | D75: Native | E75: Output Validation | F75: Critical | G75: taint | H75: agent, tool | I75: llm_output | J75: dynamic_code | L75: LLM-generated code executed | M75: Direct model-output-to-code-execution-sink rule. | N75: Never execute untrusted generated code; sandbox only where explicitly designed | O75: LLM output | P75: eval/exec/interpreter/notebook execution | Q75: rules/builtin/output_validation.yaml | R75: https://github.com/akarshkn17/AgentGuard/blob/main/rules/builtin/output_validation.yaml | S75: SEC_06 (Structured Output Schema + Tool Name Auth); SEC_18 (Human-in-the-Loop for High-Risk Actions); SEC_05 (Output Content Scanning)
A76: AIR-OUT-005 | B76: LLM-generated structured data used without schema validation | C76: agentguard | D76: Native | E76: Output Validation | F76: High | G76: taint | H76: agent, tool | I76: llm_output | K76: schema_validation | L76: LLM-generated structured data used without schema validation | M76: Flag parse-and-use flows where parsed model output reaches sensitive sink and no validator dominates. | N76: Strict schema/type/enum/range validation | O76: LLM JSON/YAML/XML output | P76: privileged SDK/API/database/tool call | Q76: rules/builtin/output_validation.yaml | R76: https://github.com/akarshkn17/AgentGuard/blob/main/rules/builtin/output_validation.yaml | S76: SEC_06 (Structured Output Schema + Tool Name Auth); SEC_05 (Output Content Scanning)
A77: AIR-OUT-006 | B77: Untrusted YAML loaded with unsafe loader | C77: agentguard | D77: Native | E77: Deserialization | F77: Critical | G77: taint | H77: agent, tool, mcp | I77: llm_output, user_input | L77: Untrusted YAML loaded with unsafe loader | M77: Flag untrusted YAML at unsafe deserialization APIs. | N77: safe_load / restricted parser | O77: User/model/tool/MCP content | P77: yaml.load unsafe loader / FullLoader where unsafe context | Q77: rules/builtin/deserialization.yaml | R77: https://github.com/akarshkn17/AgentGuard/blob/main/rules/builtin/deserialization.yaml | S77: SEC_11 (CI/CD Gates - Secret Scan, SAST, Signed Skills, Pinned Models); SEC_05 (Output Content Scanning)
A78: AIR-OUT-007 | B78: Untrusted XML parsed with unsafe external entity settings | C78: agentguard | D78: Native | E78: Deserialization | F78: High | G78: taint | H78: agent, tool, mcp | L78: Untrusted XML parsed with unsafe external entity settings | M78: Flag untrusted XML parser configurations permitting external entities/network access. | N78: Disable DTD/external entities; hardened parser | O78: Tool/MCP/user XML | P78: unsafe XML parser | Q78: rules/builtin/deserialization.yaml | R78: https://github.com/akarshkn17/AgentGuard/blob/main/rules/builtin/deserialization.yaml | S78: SEC_11 (CI/CD Gates - Secret Scan, SAST, Signed Skills, Pinned Models); SEC_05 (Output Content Scanning)
A79: AIR-PROMPT-001 | B79: Untrusted input concatenated into system/developer prompt | C79: agentguard | D79: Native | E79: Prompt Boundary | F79: Critical | G79: taint | H79: agent, llm_app | I79: retrieval, tool_result, user_input | J79: privileged_prompt | L79: Untrusted input concatenated into system/developer prompt | M79: Flag source reaching system/developer prompt via string concat, f-string, template interpolation, format(), join(), or message mutation. | N79: Keep untrusted content in user/data channel; explicit trust boundary | O79: HTTP/query/body/chat/user input, tool result, retrieved document | P79: system/developer message content or privileged prompt template | Q79: rules/builtin/prompt_boundary.yaml | R79: https://github.com/akarshkn17/AgentGuard/blob/main/rules/builtin/prompt_boundary.yaml | S79: SEC_02 (Prompt Injection & Jailbreak Detection on User Input); ENC_06 (System Prompt Integrity Protection); SEC_01 (Unified Guardrail Backend - GuardrailService); IR_01 (Multi-Level Kill-Switch Model)
A80: AIR-PROMPT-002 | B80: Retrieved content promoted to privileged instruction | C80: agentguard | D80: Native | E80: Prompt Boundary | F80: Critical | G80: taint | H80: rag, agent | I80: retrieval | J80: privileged_prompt | L80: Retrieved content promoted to privileged instruction | M80: Flag retriever/document output assigned to SystemMessage/developer role or prepended to privileged instructions. | N80: Retrieved content must remain untrusted data; delimit and policy-filter | O80: Retriever/vector DB/web/file/email/ticket/document content | P80: system/developer prompt or planner instruction field | Q80: rules/builtin/prompt_boundary.yaml | R80: https://github.com/akarshkn17/AgentGuard/blob/main/rules/builtin/prompt_boundary.yaml | S80: SEC_03 (Indirect Injection Defense - Tool Output Sanitisation); DATA_06 (RAG Source Trust Classification); SEC_01 (Unified Guardrail Backend - GuardrailService); IR_01 (Multi-Level Kill-Switch Model)
A81: AIR-PROMPT-003 | B81: Tool output promoted to privileged instruction | C81: agentguard | D81: Native | E81: Prompt Boundary | F81: Critical | G81: taint | H81: agent, tool | J81: privileged_prompt | K81: schema_validation | L81: Tool output promoted to privileged instruction | M81: Flag tool result reaching privileged prompt role without validation or fixed wrapper. | N81: Tool output treated as data with schema/trust validation | O81: Tool/MCP/plugin return value | P81: system/developer prompt, policy prompt, planner instruction | Q81: rules/builtin/prompt_boundary.yaml | R81: https://github.com/akarshkn17/AgentGuard/blob/main/rules/builtin/prompt_boundary.yaml | S81: SEC_03 (Indirect Injection Defense - Tool Output Sanitisation); SEC_01 (Unified Guardrail Backend - GuardrailService); MON_04 (Tool Invocation Monitoring + Auto-Response); IR_01 (Multi-Level Kill-Switch Model)
A82: AIR-PROMPT-004 | B82: Prompt-only authorization for privileged action | C82: agentguard | D82: Native | E82: Prompt Boundary | F82: Critical | G82: control_flow | H82: agent, llm_app | K82: rbac_check | L82: Prompt-only authorization for privileged action | M82: Flag privileged sink where only dominating safety condition is model/system-prompt text and no code-level authorization check exists. | N82: Deterministic RBAC/ABAC/policy check outside the model | O82: Natural-language policy such as 'only admins may...' in system prompt | P82: Privileged tool/action call | Q82: rules/builtin/prompt_boundary.yaml | R82: https://github.com/akarshkn17/AgentGuard/blob/main/rules/builtin/prompt_boundary.yaml | S82: IAM_04 (User Identity Propagation - AgentAuthContext); SEC_18 (Human-in-the-Loop for High-Risk Actions); SEC_21 (Policy-as-Code for AI Controls)
A83: AIR-PROMPT-005 | B83: LLM output used as authorization decision | C83: agentguard | D83: Native | E83: Prompt Boundary | F83: Critical | G83: taint | H83: agent, llm_app | I83: llm_output | J83: authorization_decision | L83: LLM output used as authorization decision | M83: Flag model output controlling authorization branch or permission mutation. | N83: Deterministic identity and policy engine | O83: LLM text/boolean/classification output | P83: allow/deny, role assignment, permission grant, authentication result | Q83: rules/builtin/prompt_boundary.yaml | R83: https://github.com/akarshkn17/AgentGuard/blob/main/rules/builtin/prompt_boundary.yaml | S83: IAM_04 (User Identity Propagation - AgentAuthContext); SEC_06 (Structured Output Schema + Tool Name Auth); MON_03 (Decision Trace Logging - Tool, Policy and Evidence Trace); IR_01 (Multi-Level Kill-Switch Model)
A84: AIR-PROMPT-006 | B84: Secrets embedded in system prompt | C84: agentguard | D84: Native | E84: Prompt Boundary | F84: Critical | G84: secret | H84: agent, llm_app | J84: privileged_prompt | L84: Secrets embedded in system prompt | M84: Run secret patterns specifically against prompt literals/templates and SystemMessage/developer content. | N84: Secret manager; never expose secret material to model context | O84: API keys, tokens, passwords, private keys, connection strings | P84: system/developer prompt literal or prompt template | Q84: rules/builtin/prompt_boundary.yaml | R84: https://github.com/akarshkn17/AgentGuard/blob/main/rules/builtin/prompt_boundary.yaml | S84: ENC_06 (System Prompt Integrity Protection); ENC_01 (Secrets Retrieval via Platform Module - No Bypass); SEC_11 (CI/CD Gates - Secret Scan, SAST, Signed Skills, Pinned Models); IR_01 (Multi-Level Kill-Switch Model)
A85: AIR-PROMPT-007 | B85: Arbitrary message-role injection | C85: agentguard | D85: Native | E85: Prompt Boundary | F85: Critical | G85: taint | H85: agent | I85: user_input | K85: allowlist | L85: Arbitrary message-role injection | M85: Flag user-controlled values used as role='system'/'developer' or entire message objects passed through without normalization. | N85: Server-side role allowlist; user content forced to user role | O85: User-controlled role/type/name fields or raw message arrays | P85: chat completion messages / agent message history | Q85: rules/builtin/prompt_boundary.yaml | R85: https://github.com/akarshkn17/AgentGuard/blob/main/rules/builtin/prompt_boundary.yaml | S85: SEC_02 (Prompt Injection & Jailbreak Detection on User Input); SEC_04 (A2A Inbound Content Filtering); ENC_06 (System Prompt Integrity Protection); IR_01 (Multi-Level Kill-Switch Model)
A86: AIR-PROMPT-008 | B86: Model-generated tool arguments used without schema validation | C86: agentguard | D86: Native | E86: Prompt Boundary | F86: High | G86: taint | H86: agent, tool | I86: llm_output | K86: schema_validation | L86: Model-generated tool arguments used without schema validation | M86: Flag model tool-call args reaching sensitive tool code when no schema validator or typed model validation dominates the call. | N86: Strict JSON schema, type/range/enum validation | O86: LLM tool/function-call arguments | P86: Tool handler parameters / SDK invocation | Q86: rules/builtin/prompt_boundary.yaml | R86: https://github.com/akarshkn17/AgentGuard/blob/main/rules/builtin/prompt_boundary.yaml | S86: SEC_06 (Structured Output Schema + Tool Name Auth); MCP_03 (MCP Schema and Argument Validation)
A87: AIR-PROMPT-009 | B87: Model output directly mutates security policy or tool allowlist | C87: agentguard | D87: Native | E87: Prompt Boundary | F87: Critical | G87: taint | H87: agent | I87: llm_output | J87: policy_mutation | L87: Model output directly mutates security policy or tool allowlist | M87: Flag model output reaching state/config fields that control permissions, enabled tools, policies, or safety settings. | N87: Control plane immutable to model; signed/admin-only changes | O87: LLM/planner output | P87: policy config, allowlist, guardrail toggle, permissions, tool registry | Q87: rules/builtin/prompt_boundary.yaml | R87: https://github.com/akarshkn17/AgentGuard/blob/main/rules/builtin/prompt_boundary.yaml | S87: SEC_21 (Policy-as-Code for AI Controls); REG_07 (Runtime Drift Detection Against Registry); IR_07 (Known-Good Rollback for Prompts, Policies, Memory and Vector Indexes); IR_01 (Multi-Level Kill-Switch Model)
A88: AIR-PROMPT-010 | B88: Untrusted tool or skill description influences privileged planning | C88: agentguard | D88: Native | E88: Prompt Boundary | F88: High | G88: taint | H88: agent, mcp, skill | K88: allowlist, signature_verification | L88: Untrusted tool or skill description influences privileged planning | M88: Flag remote/mutable descriptions auto-inserted into model context when tool can perform sensitive actions and source is not allowlisted/pinned. | N88: Trusted registry, signature/allowlist, metadata sanitization | O88: Remote MCP metadata, skill markdown, plugin manifest, tool description | P88: planner/tool-selection prompt | Q88: rules/builtin/prompt_boundary.yaml | R88: https://github.com/akarshkn17/AgentGuard/blob/main/rules/builtin/prompt_boundary.yaml | S88: SEC_03 (Indirect Injection Defense - Tool Output Sanitisation); SEC_12 (Safety Evaluation Gate - Severity-Based Release Blocking); REG_02 (Agent Manifest Schema Validation)
A89: AIR-RAG-001 | B89: Untrusted documents indexed without trust classification or sanitization | C89: agentguard | D89: Native | E89: RAG | F89: High | G89: taint | H89: rag_ingestion | I89: retrieval | J89: vector_write | K89: allowlist, approval_gate | L89: Untrusted documents indexed without trust classification or sanitization | M89: Flag external source reaching vector-store ingestion with no validation/trust-processing function. | N89: Trust label, content sanitization, source allowlist, approval | O89: Web/upload/email/ticket/wiki/external file | P89: embedding/vector-store add/upsert | Q89: rules/builtin/rag.yaml | R89: https://github.com/akarshkn17/AgentGuard/blob/main/rules/builtin/rag.yaml | S89: DATA_06 (RAG Source Trust Classification); SEC_10 (Document Screening for File-Typed Outputs); DATA_05 (Memory Write Scanning (Poisoning Defense))
A90: AIR-RAG-002 | B90: Missing tenant/user filter on vector retrieval | C90: agentguard | D90: Native | E90: RAG | F90: Critical | G90: config | H90: rag, vector_db | L90: Missing tenant/user filter on vector retrieval | M90: Flag multi-user app retriever calls lacking filter/namespace bound to identity. | N90: Mandatory tenant/user metadata filter | O90: Authenticated tenant/user identity | P90: similarity_search/query/search | Q90: rules/builtin/rag.yaml | R90: https://github.com/akarshkn17/AgentGuard/blob/main/rules/builtin/rag.yaml | S90: DATA_11 (Document/Chunk-Level RAG Authorization); MEM_02 (Memory Read Authorization and ACL Filtering); IAM_04 (User Identity Propagation - AgentAuthContext)
A91: AIR-RAG-003 | B91: User controls metadata filter operators directly | C91: agentguard | D91: Native | E91: RAG | F91: High | G91: taint | H91: rag, vector_db | I91: user_input | J91: vector_write | K91: allowlist, schema_validation | L91: User controls metadata filter operators directly | M91: Flag tainted filter object passed through to vector/search backend. | N91: Schema and field/operator allowlist | O91: Request/model filter object | P91: vector DB filter/query | Q91: rules/builtin/rag.yaml | R91: https://github.com/akarshkn17/AgentGuard/blob/main/rules/builtin/rag.yaml | S91: DATA_11 (Document/Chunk-Level RAG Authorization); SEC_06 (Structured Output Schema + Tool Name Auth); MEM_02 (Memory Read Authorization and ACL Filtering)
A92: AIR-RAG-004 | B92: Retrieved text directly controls tool/action execution | C92: agentguard | D92: Native | E92: RAG | F92: Critical | G92: taint | H92: rag | I92: retrieval | J92: shell_execution, sql_query, network_request, file_write | L92: Retrieved text directly controls tool/action execution | M92: Cross-component taint: retriever -> model -> privileged sink without approval/policy guard. | N92: Injection-resistant boundary + deterministic policy | O92: retriever/document output | P92: command/query/file/network/privileged tool sink via model | Q92: rules/builtin/rag.yaml | R92: https://github.com/akarshkn17/AgentGuard/blob/main/rules/builtin/rag.yaml | S92: SEC_03 (Indirect Injection Defense - Tool Output Sanitisation); SEC_18 (Human-in-the-Loop for High-Risk Actions); DATA_06 (RAG Source Trust Classification)
A93: AIR-RAG-005 | B93: Sensitive source documents embedded using external provider without control | C93: agentguard | D93: Native | E93: RAG | F93: High | G93: taint | H93: rag | I93: sensitive_data | J93: network_request | K93: redaction | L93: Sensitive source documents embedded using external provider without control | M93: Flag sensitive file/data source to external embeddings client without redaction or approved classification. | N93: Redaction/classification + approved provider policy | O93: PII/secrets/internal docs | P93: external embedding API | Q93: rules/builtin/rag.yaml | R93: https://github.com/akarshkn17/AgentGuard/blob/main/rules/builtin/rag.yaml | S93: DATA_07 (Data Residency & Region Pinning); DATA_08 (Restricted Data Business-Owner Sign-Off); DATA_03 (DLP at Prompt Assembly Time); NET_06 (Per-Agent Egress Allowlist)
A94: AIR-RAG-006 | B94: Raw untrusted content persisted into long-term memory | C94: agentguard | D94: Native | E94: Memory | F94: High | G94: taint | H94: agent_memory | I94: retrieval | J94: memory_write, vector_write | L94: Raw untrusted content persisted into long-term memory | M94: Flag raw external content written to long-term memory without validation/trust labeling. | N94: Sanitize, trust-label, TTL, ownership metadata | O94: User/tool/web/retrieval content | P94: persistent memory save/store/upsert | Q94: rules/builtin/memory.yaml | R94: https://github.com/akarshkn17/AgentGuard/blob/main/rules/builtin/memory.yaml | S94: DATA_05 (Memory Write Scanning (Poisoning Defense)); MEM_03 (Memory Write Validation and Provenance); MEM_07 (Memory Anomaly Detection)
A95: AIR-RAG-007 | B95: Shared persistent memory lacks tenant/agent namespace | C95: agentguard | D95: Native | E95: Memory | F95: Critical | G95: config | H95: agent_memory | J95: memory_write | L95: Shared persistent memory lacks tenant/agent namespace | M95: Flag global/static memory collections or keys in multi-user/multi-agent code. | N95: Namespace keyed by authenticated tenant/user/agent | O95: User/agent identity | P95: memory store key/collection/session | Q95: rules/builtin/memory.yaml | R95: https://github.com/akarshkn17/AgentGuard/blob/main/rules/builtin/memory.yaml | S95: MEM_02 (Memory Read Authorization and ACL Filtering); MEM_01 (Memory Store Classification and Ownership); MEM_06 (Vector Index ACL and Deletion Propagation)
A96: AIR-RAG-008 | B96: Secrets persisted in agent memory | C96: agentguard | D96: Native | E96: Memory | F96: High | G96: taint | H96: agent_memory | J96: memory_write, vector_write | K96: redaction | L96: Secrets persisted in agent memory | M96: Sensitive-source-to-memory-sink taint rule. | N96: Redact before persistence | O96: API keys, passwords, tokens, private data | P96: memory save/checkpoint/vector memory | Q96: rules/builtin/memory.yaml | R96: https://github.com/akarshkn17/AgentGuard/blob/main/rules/builtin/memory.yaml | S96: MEM_08 (Memory Minimization by Design); DATA_05 (Memory Write Scanning (Poisoning Defense)); ENC_01 (Secrets Retrieval via Platform Module - No Bypass)
A97: AIR-RAG-009 | B97: User-controlled loader type enables unsafe local/network access | C97: agentguard | D97: Native | E97: RAG | F97: High | G97: taint | H97: document_loader | I97: llm_output, user_input | K97: allowlist | L97: User-controlled loader type enables unsafe local/network access | M97: Flag tainted loader class/type or URI scheme controlling loader selection. | N97: Allowlisted loader types and schemes | O97: User/model-selected loader/scheme/type | P97: generic document loader factory | Q97: rules/builtin/rag.yaml | R97: https://github.com/akarshkn17/AgentGuard/blob/main/rules/builtin/rag.yaml | S97: REG_02 (Agent Manifest Schema Validation)
A98: AIR-RAG-010 | B98: Crawler follows redirects into private/internal networks | C98: agentguard | D98: Native | E98: RAG | F98: High | G98: taint | H98: web_crawler, loader | I98: url_input | L98: Crawler follows redirects into private/internal networks | M98: Flag generic crawler with redirects enabled and no per-hop SSRF validation. | N98: Revalidate each redirect target; block private/link-local networks | O98: External URL | P98: crawler/browser/fetch with redirects | Q98: rules/builtin/rag.yaml | R98: https://github.com/akarshkn17/AgentGuard/blob/main/rules/builtin/rag.yaml | S98: NET_06 (Per-Agent Egress Allowlist); DATA_06 (RAG Source Trust Classification)
A99: AIR-SECRET-001 | B99: Hardcoded AI provider or tool credential | C99: agentguard | D99: Native | E99: Secrets | F99: Critical | G99: secret | H99: agent, tool, mcp, skill | L99: Hardcoded AI provider or tool credential | M99: Secret scanner tuned for OpenAI, Anthropic, Google, AWS, Azure, Hugging Face, GitHub, Slack and generic bearer credentials. | N99: Secret manager/environment reference | O99: N/A | P99: source/config literals | Q99: rules/builtin/secrets.yaml | R99: https://github.com/akarshkn17/AgentGuard/blob/main/rules/builtin/secrets.yaml | S99: ENC_01 (Secrets Retrieval via Platform Module - No Bypass); IAM_02 (Workload Identity - Zero Static Key Files); SEC_11 (CI/CD Gates - Secret Scan, SAST, Signed Skills, Pinned Models)
A100: AIR-SECRET-002 | B100: API token included in URL/query string | C100: agentguard | D100: Native | E100: Secrets | F100: High | G100: taint | H100: agent, tool | I100: sensitive_data | J100: network_request | K100: authorization_check | L100: API token included in URL/query string | M100: Flag secret variables/literals concatenated into query parameters or URLs. | N100: Authorization header or secure credential mechanism | O100: Secret/token | P100: URL construction / HTTP request | Q100: rules/builtin/secrets.yaml | R100: https://github.com/akarshkn17/AgentGuard/blob/main/rules/builtin/secrets.yaml | S100: ENC_02 (No Tokens/Auth Codes in Logs); MON_02 (Prompt/Response Logging - Privacy-Safe Restricted Sink); NET_12 (Data Exfiltration Perimeter (Egress DLP))
...

Sheet entity
A1: Entity_Type | B1: What it represents | C1: Typical discovery evidence | D1: Version signal
A2: agent | B2: LLM-backed autonomous or semi-autonomous agent | C2: Agent()/RealtimeAgent()/framework agent constructor, agent config | D2: Definition hash + framework/model version + Git commit
A3: sub_agent | B3: Agent invoked/delegated by another agent | C3: handoffs, graph nodes, agents-as-tools, delegation config | D3: Definition hash + parent relationship + Git commit
A4: orchestrator | B4: Coordinator/planner/router supervising agents | C4: StateGraph/supervisor/router/planner constructs | D4: Graph/config hash + framework version
A5: tool | B5: Local function/API callable by an agent | C5: @tool, @function_tool, tool wrappers, bound tool lists | D5: Function hash + schema/signature hash
A6: function_tool | B6: Function-call tool with typed schema | C6: SDK function-tool decorators / JSON schema | D6: Function + schema hash
A7: mcp_server | B7: Model Context Protocol server | C7: MCPServer / legacy FastMCP / MCP server config | D7: Server definition hash + MCP package/spec version
A8: mcp_client | B8: MCP client connection/integration | C8: stdio/Streamable HTTP/SSE client creation | D8: Endpoint/config hash + MCP package version
A9: mcp_tool | B9: Tool exposed by an MCP server | C9: @mcp.tool / @server.tool | D9: Function/schema hash
A10: mcp_resource | B10: Resource exposed by MCP | C10: @mcp.resource / resources config | D10: Resource handler/template hash
A11: mcp_prompt | B11: Prompt exposed by MCP | C11: @mcp.prompt / prompt config | D11: Prompt handler/template hash
A12: skill | B12: Skill/instruction bundle consumed by an agent | C12: SKILL.md, skill YAML/JSON, referenced scripts | D12: Skill content hash + referenced artifact hashes
... A29: remote_agent | B29: Externally hosted/remote agent capability | C29: agent endpoint, remote agent config/card | D29: Endpoint + advertised capability/version

Sheet Source Summary
A1: Source File | B1: Engine | C1: Rule Set | D1: Rule Count | E1: Critical | F1: High | G1: Medium | H1: Low
A2: rules/custom/example.yaml | B2: agentguard | C2: Custom | D2: =COUNTIF('Risk_rule Catalog'!$Q$2:$Q$182,A2) -> 1 | E2: =COUNTIFS('Risk_rule Catalog'!$Q$2:$Q$182,A2,'Risk_rule Catalog'!$F$2:$F$182,"Critical") -> 1 | F2: =COUNTIFS('Risk_rule Catalog'!$Q$2:$Q$182,A2,'Risk_rule Catalog'!$F$2:$F$182,"High") -> 0 | G2: =COUNTIFS('Risk_rule Catalog'!$Q$2:$Q$182,A2,'Risk_rule Catalog'!$F$2:$F$182,"Medium") -> 0 | H2: =COUNTIFS('Risk_rule Catalog'!$Q$2:$Q$182,A2,'Risk_rule Catalog'!$F$2:$F$182,"Low") -> 0
A3: rules/integrations/skillspector.yaml | B3: skillspector | C3: Integration | D3: =COUNTIF('Risk_rule Catalog'!$Q$2:$Q$182,A3) -> 68 | E3: =COUNTIFS('Risk_rule Catalog'!$Q$2:$Q$182,A3,'Risk_rule Catalog'!$F$2:$F$182,"Critical") -> 8 | F3: =COUNTIFS('Risk_rule Catalog'!$Q$2:$Q$182,A3,'Risk_rule Catalog'!$F$2:$F$182,"High") -> 36 | G3: =COUNTIFS('Risk_rule Catalog'!$Q$2:$Q$182,A3,'Risk_rule Catalog'!$F$2:$F$182,"Medium") -> 21 | H3: =COUNTIFS('Risk_rule Catalog'!$Q$2:$Q$182,A3,'Risk_rule Catalog'!$F$2:$F$182,"Low") -> 3
A4: rules/builtin/agent_orchestration.yaml | B4: agentguard | C4: Native | D4: =COUNTIF('Risk_rule Catalog'!$Q$2:$Q$182,A4) -> 10 | E4: =COUNTIFS('Risk_rule Catalog'!$Q$2:$Q$182,A4,'Risk_rule Catalog'!$F$2:$F$182,"Critical") -> 4 | F4: =COUNTIFS('Risk_rule Catalog'!$Q$2:$Q$182,A4,'Risk_rule Catalog'!$F$2:$F$182,"High") -> 5 | G4: =COUNTIFS('Risk_rule Catalog'!$Q$2:$Q$182,A4,'Risk_rule Catalog'!$F$2:$F$182,"Medium") -> 1 | H4: =COUNTIFS('Risk_rule Catalog'!$Q$2:$Q$182,A4,'Risk_rule Catalog'!$F$2:$F$182,"Low") -> 0
A5: rules/builtin/archive.yaml | B5: agentguard | C5: Native | D5: =COUNTIF('Risk_rule Catalog'!$Q$2:$Q$182,A5) -> 1 | E5: =COUNTIFS('Risk_rule Catalog'!$Q$2:$Q$182,A5,'Risk_rule Catalog'!$F$2:$F$182,"Critical") -> 0 | F5: =COUNTIFS('Risk_rule Catalog'!$Q$2:$Q$182,A5,'Risk_rule Catalog'!$F$2:$F$182,"High") -> 1 | G5: =COUNTIFS('Risk_rule Catalog'!$Q$2:$Q$182,A5,'Risk_rule Catalog'!$F$2:$F$182,"Medium") -> 0 | H5: =COUNTIFS('Risk_rule Catalog'!$Q$2:$Q$182,A5,'Risk_rule Catalog'!$F$2:$F$182,"Low") -> 0
A6: rules/builtin/authorization.yaml | B6: agentguard | C6: Native | D6: =COUNTIF('Risk_rule Catalog'!$Q$2:$Q$182,A6) -> 7 | E6: =COUNTIFS('Risk_rule Catalog'!$Q$2:$Q$182,A6,'Risk_rule Catalog'!$F$2:$F$182,"Critical") -> 5 | F6: =COUNTIFS('Risk_rule Catalog'!$Q$2:$Q$182,A6,'Risk_rule Catalog'!$F$2:$F$182,"High") -> 2 | G6: =COUNTIFS('Risk_rule Catalog'!$Q$2:$Q$182,A6,'Risk_rule Catalog'!$F$2:$F$182,"Medium") -> 0 | H6: =COUNTIFS('Risk_rule Catalog'!$Q$2:$Q$182,A6,'Risk_rule Catalog'!$F$2:$F$182,"Low") -> 0
A7: rules/builtin/cloud_config.yaml | B7: agentguard | C7: Native | D7: =COUNTIF('Risk_rule Catalog'!$Q$2:$Q$182,A7) -> 4 | E7: =COUNTIFS('Risk_rule Catalog'!$Q$2:$Q$182,A7,'Risk_rule Catalog'!$F$2:$F$182,"Critical") -> 3 | F7: =COUNTIFS('Risk_rule Catalog'!$Q$2:$Q$182,A7,'Risk_rule Catalog'!$F$2:$F$182,"High") -> 1 | G7: =COUNTIFS('Risk_rule Catalog'!$Q$2:$Q$182,A7,'Risk_rule Catalog'!$F$2:$F$182,"Medium") -> 0 | H7: =COUNTIFS('Risk_rule Catalog'!$Q$2:$Q$182,A7,'Risk_rule Catalog'!$F$2:$F$182,"Low") -> 0
A8: rules/builtin/code_execution.yaml | B8: agentguard | C8: Native | D8: =COUNTIF('Risk_rule Catalog'!$Q$2:$Q$182,A8) -> 6 | E8: =COUNTIFS('Risk_rule Catalog'!$Q$2:$Q$182,A8,'Risk_rule Catalog'!$F$2:$F$182,"Critical") -> 4 | F8: =COUNTIFS('Risk_rule Catalog'!$Q$2:$Q$182,A8,'Risk_rule Catalog'!$F$2:$F$182,"High") -> 2 | G8: =COUNTIFS('Risk_rule Catalog'!$Q$2:$Q$182,A8,'Risk_rule Catalog'!$F$2:$F$182,"Medium") -> 0 | H8: =COUNTIFS('Risk_rule Catalog'!$Q$2:$Q$182,A8,'Risk_rule Catalog'!$F$2:$F$182,"Low") -> 0
A9: rules/builtin/data_exfiltration.yaml | B9: agentguard | C9: Native | D9: =COUNTIF('Risk_rule Catalog'!$Q$2:$Q$182,A9) -> 1 | E9: =COUNTIFS('Risk_rule Catalog'!$Q$2:$Q$182,A9,'Risk_rule Catalog'!$F$2:$F$182,"Critical") -> 1 | F9: =COUNTIFS('Risk_rule Catalog'!$Q$2:$Q$182,A9,'Risk_rule Catalog'!$F$2:$F$182,"High") -> 0 | G9: =COUNTIFS('Risk_rule Catalog'!$Q$2:$Q$182,A9,'Risk_rule Catalog'!$F$2:$F$182,"Medium") -> 0 | H9: =COUNTIFS('Risk_rule Catalog'!$Q$2:$Q$182,A9,'Risk_rule Catalog'!$F$2:$F$182,"Low") -> 0
A10: rules/builtin/debug_exposure.yaml | B10: agentguard | C10: Native | D10: =COUNTIF('Risk_rule Catalog'!$Q$2:$Q$182,A10) -> 1 | E10: =COUNTIFS('Risk_rule Catalog'!$Q$2:$Q$182,A10,'Risk_rule Catalog'!$F$2:$F$182,"Critical") -> 0 | F10: =COUNTIFS('Risk_rule Catalog'!$Q$2:$Q$182,A10,'Risk_rule Catalog'!$F$2:$F$182,"High") -> 1 | G10: =COUNTIFS('Risk_rule Catalog'!$Q$2:$Q$182,A10,'Risk_rule Catalog'!$F$2:$F$182,"Medium") -> 0 | H10: =COUNTIFS('Risk_rule Catalog'!$Q$2:$Q$182,A10,'Risk_rule Catalog'!$F$2:$F$182,"Low") -> 0
A11: rules/builtin/deserialization.yaml | B11: agentguard | C11: Native | D11: =COUNTIF('Risk_rule Catalog'!$Q$2:$Q$182,A11) -> 2 | E11: =COUNTIFS('Risk_rule Catalog'!$Q$2:$Q$182,A11,'Risk_rule Catalog'!$F$2:$F$182,"Critical") -> 1 | F11: =COUNTIFS('Risk_rule Catalog'!$Q$2:$Q$182,A11,'Risk_rule Catalog'!$F$2:$F$182,"High") -> 1 | G11: =COUNTIFS('Risk_rule Catalog'!$Q$2:$Q$182,A11,'Risk_rule Catalog'!$F$2:$F$182,"Medium") -> 0 | H11: =COUNTIFS('Risk_rule Catalog'!$Q$2:$Q$182,A11,'Risk_rule Catalog'!$F$2:$F$182,"Low") -> 0
A12: rules/builtin/file_access.yaml | B12: agentguard | C12: Native | D12: =COUNTIF('Risk_rule Catalog'!$Q$2:$Q$182,A12) -> 4 | E12: =COUNTIFS('Risk_rule Catalog'!$Q$2:$Q$182,A12,'Risk_rule Catalog'!$F$2:$F$182,"Critical") -> 1 | F12: =COUNTIFS('Risk_rule Catalog'!$Q$2:$Q$182,A12,'Risk_rule Catalog'!$F$2:$F$182,"High") -> 3 | G12: =COUNTIFS('Risk_rule Catalog'!$Q$2:$Q$182,A12,'Risk_rule Catalog'!$F$2:$F$182,"Medium") -> 0 | H12: =COUNTIFS('Risk_rule Catalog'!$Q$2:$Q$182,A12,'Risk_rule Catalog'!$F$2:$F$182,"Low") -> 0
A13: rules/builtin/file_upload.yaml | B13: agentguard | C13: Native | D13: =COUNTIF('Risk_rule Catalog'!$Q$2:$Q$182,A13) -> 1 | E13: =COUNTIFS('Risk_rule Catalog'!$Q$2:$Q$182,A13,'Risk_rule Catalog'!$F$2:$F$182,"Critical") -> 1 | F13: =COUNTIFS('Risk_rule Catalog'!$Q$2:$Q$182,A13,'Risk_rule Catalog'!$F$2:$F$182,"High") -> 0 | G13: =COUNTIFS('Risk_rule Catalog'!$Q$2:$Q$182,A13,'Risk_rule Catalog'!$F$2:$F$182,"Medium") -> 0 | H13: =COUNTIFS('Risk_rule Catalog'!$Q$2:$Q$182,A13,'Risk_rule Catalog'!$F$2:$F$182,"Low") -> 0
... A27: rules/builtin/tls.yaml | B27: agentguard | C27: Native | D27: =COUNTIF('Risk_rule Catalog'!$Q$2:$Q$182,A27) -> 1 | E27: =COUNTIFS('Risk_rule Catalog'!$Q$2:$Q$182,A27,'Risk_rule Catalog'!$F$2:$F$182,"Critical") -> 0 | F27: =COUNTIFS('Risk_rule Catalog'!$Q$2:$Q$182,A27,'Risk_rule Catalog'!$F$2:$F$182,"High") -> 1 | G27: =COUNTIFS('Risk_rule Catalog'!$Q$2:$Q$182,A27,'Risk_rule Catalog'!$F$2:$F$182,"Medium") -> 0 | H27: =COUNTIFS('Risk_rule Catalog'!$Q$2:$Q$182,A27,'Risk_rule Catalog'!$F$2:$F$182,"Low") -> 0
